{
  "directed": true,
  "multigraph": false,
  "graph": {},
  "nodes": [
    {
      "id": "floor:1",
      "centrality": 2.0
    },
    {
      "id": "wall:2",
      "centrality": 1.2795855601643407
    },
    {
      "id": "wall:3",
      "centrality": 0.0
    },
    {
      "id": "cabinet:4",
      "centrality": 1.167221069235542
    },
    {
      "id": "wall:5",
      "centrality": 0.5435325914579753
    },
    {
      "id": "curtain:6",
      "centrality": 0.24571980808531158
    },
    {
      "id": "wall:7",
      "centrality": 0.0
    },
    {
      "id": "table:8",
      "centrality": 0.2685048006965592
    },
    {
      "id": "chair:9",
      "centrality": 0.0
    },
    {
      "id": "chair:10",
      "centrality": 0.0
    },
    {
      "id": "cabinet:11",
      "centrality": 0.11937380250892492
    },
    {
      "id": "cabinet:12",
      "centrality": 0.35070581355647357
    },
    {
      "id": "counter:13",
      "centrality": 1.9735963692465666
    },
    {
      "id": "wall:14",
      "centrality": 0.4464964887731734
    },
    {
      "id": "cabinet:15",
      "centrality": 0.0
    },
    {
      "id": "cabinet:16",
      "centrality": 0.2704351337844247
    },
    {
      "id": "wall:17",
      "centrality": 0.0
    },
    {
      "id": "object:18",
      "centrality": 0.21487769981189703
    },
    {
      "id": "shelf:19",
      "centrality": 0.0
    },
    {
      "id": "object:20",
      "centrality": 0.0
    },
    {
      "id": "-:21",
      "centrality": 0.0
    },
    {
      "id": "-:22",
      "centrality": 0.0
    },
    {
      "id": "sink:23",
      "centrality": 0.0
    },
    {
      "id": "-:25",
      "centrality": 0.0
    },
    {
      "id": "-:26",
      "centrality": 0.0
    },
    {
      "id": "lamp:29",
      "centrality": 0.0
    },
    {
      "id": "object:32",
      "centrality": 0.0
    },
    {
      "id": "ceiling:35",
      "centrality": 0.2796279392282628
    }
  ],
  "links": [
    {
      "type": "weak_touching",
      "weight": 0.03140814158174275,
      "weight_inv": 31.838878381180322,
      "overlap_obb": 0.0628162831634855,
      "overlap_geometry": 0.0,
      "center_difference": [
        1.9678986594673165,
        -0.02229559523637903,
        0.8913941251591344
      ],
      "log_obb_volume_ratio": 0.8075546465229053,
      "log_geom_volume_ratio": 0.6142741979574735,
      "source": "wall:2",
      "target": "ceiling:35"
    },
    {
      "type": "touching",
      "weight": 0.05738344877529519,
      "weight_inv": 17.42662773574044,
      "overlap_obb": 0.1147186230618474,
      "overlap_geometry": 4.8274488742992657e-05,
      "center_difference": [
        0.38702035771480814,
        -1.3252429741500866,
        -1.235998895900187
      ],
      "log_obb_volume_ratio": 0.1493309336076677,
      "log_geom_volume_ratio": 1.5106698147504503,
      "source": "wall:3",
      "target": "floor:1"
    },
    {
      "type": "touching",
      "weight": 0.037684021155183524,
      "weight_inv": 26.536446200419558,
      "overlap_obb": 0.0750059836447946,
      "overlap_geometry": 0.00036205866557244493,
      "center_difference": [
        -1.1107564293551144,
        -0.7421187864513751,
        -0.06896669418535709
      ],
      "log_obb_volume_ratio": 0.7351240474026975,
      "log_geom_volume_ratio": 1.094432001596497,
      "source": "wall:3",
      "target": "curtain:6"
    },
    {
      "type": "touching",
      "weight": 0.10525840178430221,
      "weight_inv": 9.500429258361928,
      "overlap_obb": 0.21044439183548994,
      "overlap_geometry": 7.241173311448898e-05,
      "center_difference": [
        -0.11200514340072276,
        -0.790489321142566,
        1.2421227067359286
      ],
      "log_obb_volume_ratio": 0.985826248315339,
      "log_geom_volume_ratio": 1.154250514804576,
      "source": "cabinet:4",
      "target": "wall:2"
    },
    {
      "type": "touching",
      "weight": 0.14131287380461147,
      "weight_inv": 7.0764960974657285,
      "overlap_obb": 0.28260161036485143,
      "overlap_geometry": 2.4137244371496328e-05,
      "center_difference": [
        0.05429474609529028,
        1.7266103328378293,
        -1.1051862487311956
      ],
      "log_obb_volume_ratio": 0.13786113212270074,
      "log_geom_volume_ratio": 2.0152460003320822,
      "source": "wall:5",
      "target": "floor:1"
    },
    {
      "type": "weak_touching",
      "weight": 0.11398936891663738,
      "weight_inv": 8.772747928197754,
      "overlap_obb": 0.22797873783327477,
      "overlap_geometry": 0.0,
      "center_difference": [
        -0.680554375610654,
        0.308221130411223,
        -0.2334884386065697
      ],
      "log_obb_volume_ratio": 0.3560824850049311,
      "log_geom_volume_ratio": 0.9236082863604372,
      "source": "wall:5",
      "target": "counter:13"
    },
    {
      "type": "touching",
      "weight": 0.10260457499879193,
      "weight_inv": 9.746154106790794,
      "overlap_obb": 0.20510053239791212,
      "overlap_geometry": 0.00010861759967173347,
      "center_difference": [
        1.4977767870699226,
        -0.5831241876987115,
        -1.16703220171483
      ],
      "log_obb_volume_ratio": 0.20313705439956165,
      "log_geom_volume_ratio": 1.3803231379809515,
      "source": "curtain:6",
      "target": "floor:1"
    },
    {
      "type": "touching",
      "weight": 0.07939008584647897,
      "weight_inv": 12.596031221502338,
      "overlap_obb": 0.15873793151530782,
      "overlap_geometry": 4.2240177650118576e-05,
      "center_difference": [
        2.192951476217327,
        -0.21154255876147576,
        -1.4048299317187647
      ],
      "log_obb_volume_ratio": 0.06967987521700443,
      "log_geom_volume_ratio": 2.2882609148164224,
      "source": "wall:7",
      "target": "floor:1"
    },
    {
      "type": "weak_touching",
      "weight": 0.1497715943838128,
      "weight_inv": 6.6768335084778885,
      "overlap_obb": 0.2995431887676256,
      "overlap_geometry": 0.0,
      "center_difference": [
        0.4728749300339603,
        -0.7842445829799516,
        -0.3931634350138461
      ],
      "log_obb_volume_ratio": 0.14096296347243475,
      "log_geom_volume_ratio": 1.499082058408095,
      "source": "wall:7",
      "target": "cabinet:4"
    },
    {
      "type": "touching",
      "weight": 0.1545241801188898,
      "weight_inv": 6.471479086513238,
      "overlap_obb": 0.3088311250384361,
      "overlap_geometry": 0.00021723519934346695,
      "center_difference": [
        0.695174689147404,
        0.3715816289372358,
        -0.23779773000393467
      ],
      "log_obb_volume_ratio": 0.34301902930987266,
      "log_geom_volume_ratio": 1.6577719027180433,
      "source": "wall:7",
      "target": "curtain:6"
    },
    {
      "type": "part_within",
      "weight": 0.2732532970022347,
      "weight_inv": 3.6596081766282285,
      "overlap_obb": 0.5464703881379122,
      "overlap_geometry": 3.620586655724449e-05,
      "center_difference": [
        0.33752520317801205,
        -0.8278087794840572,
        -0.4199989338553256
      ],
      "log_obb_volume_ratio": -0.03308874052949548,
      "log_geom_volume_ratio": 1.9548169413791017,
      "source": "table:8",
      "target": "floor:1"
    },
    {
      "type": "weak_touching",
      "weight": 0.1422784521592615,
      "weight_inv": 7.028471176230082,
      "overlap_obb": 0.284556904318523,
      "overlap_geometry": 0.0,
      "center_difference": [
        -0.32145652349289033,
        -1.1860685523961796,
        -0.6242360219460861
      ],
      "log_obb_volume_ratio": -0.4110199839432978,
      "log_geom_volume_ratio": 2.2906372637871044,
      "source": "chair:9",
      "target": "floor:1"
    },
    {
      "type": "touching",
      "weight": 0.1163955202330739,
      "weight_inv": 8.591395940303974,
      "overlap_obb": 0.23268845717756892,
      "overlap_geometry": 0.0001025832885788594,
      "center_difference": [
        -0.6589817266709024,
        -0.3582597729121224,
        -0.20423708809076047
      ],
      "log_obb_volume_ratio": 12.421747620672125,
      "log_geom_volume_ratio": 1.1717911868366995,
      "source": "chair:9",
      "target": "table:8"
    },
    {
      "type": "weak_touching",
      "weight": 0.20089792576761428,
      "weight_inv": 4.977652189185544,
      "overlap_obb": 0.40179585153522857,
      "overlap_geometry": 0.0,
      "center_difference": [
        0.9474700210677467,
        -0.4779403862713783,
        -0.5379053337954047
      ],
      "log_obb_volume_ratio": -0.11749012842117743,
      "log_geom_volume_ratio": 2.4248171468551263,
      "source": "chair:10",
      "target": "floor:1"
    },
    {
      "type": "touching",
      "weight": 0.13815044149747024,
      "weight_inv": 7.2384857345411495,
      "overlap_obb": 0.2762345055729189,
      "overlap_geometry": 6.63774220216149e-05,
      "center_difference": [
        -0.550306766002176,
        0.10518380142733325,
        0.6291268679194253
      ],
      "log_obb_volume_ratio": -0.5783786161931812,
      "log_geom_volume_ratio": 1.756702528657162,
      "source": "chair:10",
      "target": "curtain:6"
    },
    {
      "type": "weak_touching",
      "weight": 0.06704526030769158,
      "weight_inv": 14.915297448480155,
      "overlap_obb": 0.13409052061538315,
      "overlap_geometry": 0.0,
      "center_difference": [
        -1.1508829642915865,
        0.49244602934927495,
        0.3305155799727427
      ],
      "log_obb_volume_ratio": -0.02945457573508885,
      "log_geom_volume_ratio": 1.562602215914638,
      "source": "cabinet:11",
      "target": "wall:2"
    },
    {
      "type": "weak_touching",
      "weight": 0.06608545785075144,
      "weight_inv": 15.131922097875414,
      "overlap_obb": 0.13217091570150288,
      "overlap_geometry": 0.0,
      "center_difference": [
        0.6269039791972124,
        0.12902704187248748,
        -0.8180873747369088
      ],
      "log_obb_volume_ratio": -0.10713044192635797,
      "log_geom_volume_ratio": 1.0254167971170984,
      "source": "cabinet:11",
      "target": "wall:5"
    },
    {
      "type": "part_within",
      "weight": 0.31385052879192094,
      "weight_inv": 3.186230094463176,
      "overlap_obb": 0.6276527830950989,
      "overlap_geometry": 4.8274488742992657e-05,
      "center_difference": [
        0.24602138350433478,
        1.2590927645533447,
        -0.4332052366537251
      ],
      "log_obb_volume_ratio": -0.06203567188755409,
      "log_geom_volume_ratio": 1.9562493108130794,
      "source": "cabinet:12",
      "target": "floor:1"
    },
    {
      "type": "part_within",
      "weight": 0.26570014191651525,
      "weight_inv": 3.7636411963762013,
      "overlap_obb": 0.5314002838330305,
      "overlap_geometry": 0.0,
      "center_difference": [
        -0.4888277382016095,
        -0.15929643787326153,
        0.43849257347090076
      ],
      "log_obb_volume_ratio": -0.1602323719858196,
      "log_geom_volume_ratio": 0.8965694874750377,
      "source": "cabinet:12",
      "target": "counter:13"
    },
    {
      "type": "weak_touching",
      "weight": 0.10641588647282313,
      "weight_inv": 9.397093170439206,
      "overlap_obb": 0.21283177294564626,
      "overlap_geometry": 0.0,
      "center_difference": [
        0.7348491217059443,
        1.4183892024266063,
        -0.8716978101246259
      ],
      "log_obb_volume_ratio": 0.3871606662169626,
      "log_geom_volume_ratio": 2.1819271547176595,
      "source": "counter:13",
      "target": "floor:1"
    },
    {
      "type": "weak_touching",
      "weight": 0.0933956136248124,
      "weight_inv": 10.707140958644873,
      "overlap_obb": 0.1867912272496248,
      "overlap_geometry": 0.0,
      "center_difference": [
        -0.9852274244774221,
        0.8456871782081304,
        0.13996868658029266
      ],
      "log_obb_volume_ratio": 0.7832292276635254,
      "log_geom_volume_ratio": 1.4294208449795933,
      "source": "counter:13",
      "target": "cabinet:4"
    },
    {
      "type": "weak_touching",
      "weight": 0.02126416731942313,
      "weight_inv": 47.027470437865645,
      "overlap_obb": 0.04252833463884626,
      "overlap_geometry": 0.0,
      "center_difference": [
        -0.7292203684836135,
        -0.44806709846444925,
        -1.0219188923659122
      ],
      "log_obb_volume_ratio": 0.4222574949604703,
      "log_geom_volume_ratio": 1.0977933598265308,
      "source": "wall:14",
      "target": "wall:5"
    },
    {
      "type": "weak_touching",
      "weight": 0.011768159373054466,
      "weight_inv": 84.97505585195407,
      "overlap_obb": 0.023536318746108932,
      "overlap_geometry": 0.0,
      "center_difference": [
        -0.5391086525050959,
        -0.10694370622404081,
        1.0180781875028737
      ],
      "log_obb_volume_ratio": 0.09375386107025653,
      "log_geom_volume_ratio": 1.0276160569947563,
      "source": "wall:14",
      "target": "ceiling:35"
    },
    {
      "type": "part_within",
      "weight": 0.29763300431441814,
      "weight_inv": 3.3598424418805535,
      "overlap_obb": 0.5951513567180716,
      "overlap_geometry": 0.00011465191076460755,
      "center_difference": [
        0.34876756234632955,
        -0.07595790054694196,
        0.38864933012193287
      ],
      "log_obb_volume_ratio": -14.160071574600305,
      "log_geom_volume_ratio": 1.1514850478145713,
      "source": "cabinet:15",
      "target": "wall:14"
    },
    {
      "type": "touching",
      "weight": 0.13411922536432141,
      "weight_inv": 7.45605260754825,
      "overlap_obb": 0.26811776450678537,
      "overlap_geometry": 0.00012068622185748163,
      "center_difference": [
        -0.9173433426528702,
        0.9157834159439112,
        -0.9808815831253805
      ],
      "log_obb_volume_ratio": 0.04482622864837487,
      "log_geom_volume_ratio": 1.5299741502909014,
      "source": "cabinet:16",
      "target": "floor:1"
    },
    {
      "type": "touching",
      "weight": 0.07023312112445437,
      "weight_inv": 14.238296461693361,
      "overlap_obb": 0.14044210500453724,
      "overlap_geometry": 2.4137244371496328e-05,
      "center_difference": [
        -0.242417720264547,
        -0.3627598184294688,
        1.1462235579717273
      ],
      "log_obb_volume_ratio": 0.7700394842991916,
      "log_geom_volume_ratio": 0.6915688539587647,
      "source": "cabinet:16",
      "target": "wall:14"
    },
    {
      "type": "part_within",
      "weight": 0.36358722746415767,
      "weight_inv": 2.7503716425203075,
      "overlap_obb": 0.7269813569733433,
      "overlap_geometry": 0.00019309795497197063,
      "center_difference": [
        -0.35128223837896,
        -0.2602086976669675,
        -0.194226962242651
      ],
      "log_obb_volume_ratio": -11.495034331067076,
      "log_geom_volume_ratio": 1.433631470035861,
      "source": "wall:17",
      "target": "cabinet:16"
    },
    {
      "type": "part_within",
      "weight": 0.44069508414231795,
      "weight_inv": 2.2691426248745272,
      "overlap_obb": 0.8813599967291715,
      "overlap_geometry": 3.017155546437041e-05,
      "center_difference": [
        -0.5394197624972791,
        0.7850806054860209,
        1.1721794897351399
      ],
      "log_obb_volume_ratio": -2.555385603840489,
      "log_geom_volume_ratio": 2.6663641357725503,
      "source": "object:18",
      "target": "wall:2"
    },
    {
      "type": "part_within",
      "weight": 0.2638572389798333,
      "weight_inv": 3.7899282349287007,
      "overlap_obb": 0.5276299976043664,
      "overlap_geometry": 8.448035530023715e-05,
      "center_difference": [
        0.5578128053808658,
        0.7298827484204564,
        -0.2099119035810813
      ],
      "log_obb_volume_ratio": -3.3095365430846506,
      "log_geom_volume_ratio": 1.6160666617853627,
      "source": "object:18",
      "target": "counter:13"
    },
    {
      "type": "part_within",
      "weight": 0.4203746617835291,
      "weight_inv": 2.378830340908957,
      "overlap_obb": 0.8407493235670582,
      "overlap_geometry": 0.0,
      "center_difference": [
        -0.04438700990005562,
        -0.09840852295012881,
        0.4130645568492338
      ],
      "log_obb_volume_ratio": -1.9958751340432626,
      "log_geom_volume_ratio": 1.9850604493077515,
      "source": "shelf:19",
      "target": "wall:2"
    },
    {
      "type": "part_within",
      "weight": 0.4079600400242802,
      "weight_inv": 2.4512204674273583,
      "overlap_obb": 0.8159200800485604,
      "overlap_geometry": 0.0,
      "center_difference": [
        0.06761813350066714,
        0.6920807981924372,
        -0.8290581498866947
      ],
      "log_obb_volume_ratio": -2.0245708992370393,
      "log_geom_volume_ratio": 1.7197830313671882,
      "source": "shelf:19",
      "target": "cabinet:4"
    },
    {
      "type": "weak_touching",
      "weight": 0.19493817489245366,
      "weight_inv": 5.129831550704189,
      "overlap_obb": 0.3898763497849073,
      "overlap_geometry": 0.0,
      "center_difference": [
        -0.784684400565803,
        0.8297882112604762,
        1.1976392286216626
      ],
      "log_obb_volume_ratio": -2.94644465333772,
      "log_geom_volume_ratio": 2.798817396693212,
      "source": "object:20",
      "target": "wall:2"
    },
    {
      "type": "part_within",
      "weight": 0.3676005036541695,
      "weight_inv": 2.7203444773861847,
      "overlap_obb": 0.73505618384211,
      "overlap_geometry": 0.00014482346622897796,
      "center_difference": [
        0.9931025429229958,
        0.4663692237836887,
        0.04903627391201121
      ],
      "log_obb_volume_ratio": -10.716634341047056,
      "log_geom_volume_ratio": 1.8366506468524992,
      "source": "object:20",
      "target": "wall:5"
    },
    {
      "type": "part_within",
      "weight": 0.288479153350754,
      "weight_inv": 3.466454987768655,
      "overlap_obb": 0.576910032212765,
      "overlap_geometry": 4.8274488742992657e-05,
      "center_difference": [
        0.3125481673123418,
        0.7745903541949117,
        -0.1844521646945585
      ],
      "log_obb_volume_ratio": -3.816005787049219,
      "log_geom_volume_ratio": 1.6963457565822255,
      "source": "object:20",
      "target": "counter:13"
    },
    {
      "type": "part_within",
      "weight": 0.28889288911980415,
      "weight_inv": 3.4614905304411945,
      "overlap_obb": 0.5777314694397725,
      "overlap_geometry": 5.430879983586674e-05,
      "center_difference": [
        -0.24526463806852394,
        0.04470760577445532,
        0.02545973888652281
      ],
      "log_obb_volume_ratio": 1.153033283473738,
      "log_geom_volume_ratio": 1.0496756084975938,
      "source": "object:20",
      "target": "object:18"
    },
    {
      "type": "touching",
      "weight": 0.17720357700794973,
      "weight_inv": 5.643226942056242,
      "overlap_obb": 0.35435887952715645,
      "overlap_geometry": 4.8274488742992657e-05,
      "center_difference": [
        0.11823636423283973,
        -0.22448897144768343,
        0.25545719752232837
      ],
      "log_obb_volume_ratio": -5.171492760685001,
      "log_geom_volume_ratio": 1.284519887345062,
      "source": "-:21",
      "target": "wall:5"
    },
    {
      "type": "part_within",
      "weight": 0.348738673087021,
      "weight_inv": 2.867476644181844,
      "overlap_obb": 0.6974230373742062,
      "overlap_geometry": 5.430879983586674e-05,
      "center_difference": [
        -0.5623180113778143,
        0.08373215896353958,
        0.021968758915758668
      ],
      "log_obb_volume_ratio": -1.841477993409727,
      "log_geom_volume_ratio": 1.1863932119466747,
      "source": "-:21",
      "target": "counter:13"
    },
    {
      "type": "within",
      "weight": 0.4999999196513925,
      "weight_inv": 2.0000003213944817,
      "overlap_obb": 0.999999839302785,
      "overlap_geometry": 0.0,
      "center_difference": [
        -0.07113190061933455,
        0.358480531318049,
        -0.06837696084509681
      ],
      "log_obb_volume_ratio": -5.806245948399176,
      "log_geom_volume_ratio": 1.9446519677256489,
      "source": "-:22",
      "target": "counter:13"
    },
    {
      "type": "part_within",
      "weight": 0.3303956296320139,
      "weight_inv": 3.026674417920643,
      "overlap_obb": 0.6607912592640278,
      "overlap_geometry": 0.0,
      "center_difference": [
        -0.05055753344309233,
        0.9372070005772982,
        0.25965711018469745
      ],
      "log_obb_volume_ratio": -1.4003210397745096,
      "log_geom_volume_ratio": 1.7953977741808307,
      "source": "sink:23",
      "target": "cabinet:4"
    },
    {
      "type": "within",
      "weight": 0.4802023126884724,
      "weight_inv": 2.0824556100144034,
      "overlap_obb": 0.9603261793327375,
      "overlap_geometry": 7.844604420736307e-05,
      "center_difference": [
        0.9346698910343297,
        0.09151982236916778,
        0.11968842360440479
      ],
      "log_obb_volume_ratio": -1.7878814915422008,
      "log_geom_volume_ratio": 1.2560316162217868,
      "source": "sink:23",
      "target": "counter:13"
    },
    {
      "type": "part_within",
      "weight": 0.35998498633419856,
      "weight_inv": 2.7778936287960407,
      "overlap_obb": 0.7199699726683971,
      "overlap_geometry": 0.0,
      "center_difference": [
        0.29599701025955694,
        1.3333187756637725,
        -0.41191812843979814
      ],
      "log_obb_volume_ratio": -0.4626796510640203,
      "log_geom_volume_ratio": 2.453569654154171,
      "source": "-:25",
      "target": "floor:1"
    },
    {
      "type": "within",
      "weight": 0.4715073541746443,
      "weight_inv": 2.120857694256884,
      "overlap_obb": 0.9425198948396729,
      "overlap_geometry": 0.0004948135096156747,
      "center_difference": [
        0.04997562675522216,
        0.07422601111042781,
        0.021287108213926986
      ],
      "log_obb_volume_ratio": 7.458283870974651,
      "log_geom_volume_ratio": 1.2542213513339922,
      "source": "-:25",
      "target": "cabinet:12"
    },
    {
      "type": "part_within",
      "weight": 0.25458314135814036,
      "weight_inv": 3.9279898687133734,
      "overlap_obb": 0.5091662827162807,
      "overlap_geometry": 0.0,
      "center_difference": [
        -0.43885211144638736,
        -0.08507042676283372,
        0.45977968168482775
      ],
      "log_obb_volume_ratio": -1.195058515589849,
      "log_geom_volume_ratio": 1.1244965941457665,
      "source": "-:25",
      "target": "counter:13"
    },
    {
      "type": "touching",
      "weight": 0.1604924230025235,
      "weight_inv": 6.230823744148199,
      "overlap_obb": 0.32096674307176837,
      "overlap_geometry": 1.8102933278622245e-05,
      "center_difference": [
        -0.6523257671793804,
        -0.22480547398172712,
        0.19364532622954106
      ],
      "log_obb_volume_ratio": 58.14370926613152,
      "log_geom_volume_ratio": 1.7372663181284242,
      "source": "-:26",
      "target": "cabinet:11"
    },
    {
      "type": "touching",
      "weight": 0.1735644878956078,
      "weight_inv": 5.761547261911438,
      "overlap_obb": 0.34708673561356546,
      "overlap_geometry": 4.2240177650118576e-05,
      "center_difference": [
        0.7037985805014455,
        0.3522886663552096,
        0.3974768438585445
      ],
      "log_obb_volume_ratio": -14.751570648856026,
      "log_geom_volume_ratio": 1.6227298587014194,
      "source": "-:26",
      "target": "wall:14"
    },
    {
      "type": "touching",
      "weight": 0.24459646583002084,
      "weight_inv": 4.088366512600951,
      "overlap_obb": 0.4891868973489488,
      "overlap_geometry": 6.034311092874082e-06,
      "center_difference": [
        0.042838880682108824,
        -0.17614576344616562,
        -0.4391783826392003
      ],
      "log_obb_volume_ratio": 47.47047809766231,
      "log_geom_volume_ratio": 1.9284044258389859,
      "source": "object:32",
      "target": "table:8"
    }
  ]
}