{
  "directed": true,
  "multigraph": false,
  "graph": {},
  "nodes": [
    {
      "id": "floor:1",
      "centrality": 1.175103947651484
    },
    {
      "id": "sofa:2",
      "centrality": 0.35786853050628936
    },
    {
      "id": "wall:3",
      "centrality": 0.03594123143810807
    },
    {
      "id": "wall:4",
      "centrality": 1.9023131821345367
    },
    {
      "id": "window:5",
      "centrality": 0.5201534285895443
    },
    {
      "id": "ceiling:6",
      "centrality": 0.21064523116327685
    },
    {
      "id": "wall:7",
      "centrality": 0.17778530549248386
    },
    {
      "id": "cabinet:8",
      "centrality": 0.016792291755358752
    },
    {
      "id": "door:9",
      "centrality": 0.0
    },
    {
      "id": "wall:10",
      "centrality": 1.9600769539859442
    },
    {
      "id": "window:11",
      "centrality": 0.5787056614648342
    },
    {
      "id": "window:12",
      "centrality": 0.2664279813107396
    },
    {
      "id": "table:13",
      "centrality": 2.0
    },
    {
      "id": "shelf:14",
      "centrality": 0.4452557827864892
    },
    {
      "id": "object:15",
      "centrality": 0.33909113310580735
    },
    {
      "id": "table:16",
      "centrality": 0.6698855297655503
    },
    {
      "id": "box:17",
      "centrality": 0.0
    },
    {
      "id": "curtain:18",
      "centrality": 0.0
    },
    {
      "id": "chair:19",
      "centrality": 0.13325738724893332
    },
    {
      "id": "object:21",
      "centrality": 0.0
    },
    {
      "id": "box:22",
      "centrality": 0.0
    },
    {
      "id": "-:23",
      "centrality": 0.0
    },
    {
      "id": "box:24",
      "centrality": 0.0
    },
    {
      "id": "object:25",
      "centrality": 0.0
    },
    {
      "id": "-:26",
      "centrality": 0.0
    },
    {
      "id": "box:27",
      "centrality": 0.0
    },
    {
      "id": "-:28",
      "centrality": 0.0
    },
    {
      "id": "window:29",
      "centrality": 0.0
    },
    {
      "id": "window:30",
      "centrality": 0.0
    },
    {
      "id": "object:31",
      "centrality": 0.0
    },
    {
      "id": "-:36",
      "centrality": 0.0
    },
    {
      "id": "sink:37",
      "centrality": 0.0
    },
    {
      "id": "window:38",
      "centrality": 0.0
    },
    {
      "id": "plant:39",
      "centrality": 0.0
    },
    {
      "id": "-:40",
      "centrality": 0.16470381425990402
    },
    {
      "id": "-:41",
      "centrality": 0.1307882993337566
    },
    {
      "id": "-:42",
      "centrality": 0.0
    },
    {
      "id": "box:43",
      "centrality": 0.25634014673857136
    }
  ],
  "links": [
    {
      "type": "weak_touching",
      "weight": 0.06530918622482765,
      "weight_inv": 15.311781662038907,
      "overlap_obb": 0.1306183724496553,
      "overlap_geometry": 0.0,
      "center_difference": [
        1.0878384443084277,
        0.5169827744028604,
        -0.5656334563411032
      ],
      "log_obb_volume_ratio": 0.4818608011417881,
      "log_geom_volume_ratio": 1.126781670745523,
      "source": "sofa:2",
      "target": "floor:1"
    },
    {
      "type": "weak_touching",
      "weight": 0.07344048699836002,
      "weight_inv": 13.616467440123738,
      "overlap_obb": 0.14688097399672004,
      "overlap_geometry": 0.0,
      "center_difference": [
        0.4998086398143349,
        0.37234970658443856,
        -0.728612088873243
      ],
      "log_obb_volume_ratio": 0.44773383959273966,
      "log_geom_volume_ratio": 1.0553373617020365,
      "source": "wall:3",
      "target": "sofa:2"
    },
    {
      "type": "touching",
      "weight": 0.022406388837781573,
      "weight_inv": 44.630127917525186,
      "overlap_obb": 0.0447854218238045,
      "overlap_geometry": 2.735585175863932e-05,
      "center_difference": [
        1.3594781348962681,
        -1.3255500488682692,
        -1.729461113102751
      ],
      "log_obb_volume_ratio": 0.8491043615121063,
      "log_geom_volume_ratio": 1.111382538162755,
      "source": "wall:4",
      "target": "floor:1"
    },
    {
      "type": "weak_touching",
      "weight": 0.027889910152433514,
      "weight_inv": 35.855260720972446,
      "overlap_obb": 0.05577982030486703,
      "overlap_geometry": 0.0,
      "center_difference": [
        1.8869163956399286,
        -0.21106250612863775,
        -0.2922083176593949
      ],
      "log_obb_volume_ratio": 0.9553233661508961,
      "log_geom_volume_ratio": 0.8647095988432463,
      "source": "wall:4",
      "target": "wall:10"
    },
    {
      "type": "part_within",
      "weight": 0.3309352180128131,
      "weight_inv": 3.02173943892935,
      "overlap_obb": 0.6618499191368072,
      "overlap_geometry": 2.051688881897949e-05,
      "center_difference": [
        0.2702823939933554,
        0.03022806385451826,
        0.2518649818098686
      ],
      "log_obb_volume_ratio": -0.8036868271857822,
      "log_geom_volume_ratio": 1.489488460638375,
      "source": "window:5",
      "target": "wall:4"
    },
    {
      "type": "touching",
      "weight": 0.12605952644260177,
      "weight_inv": 7.932760246051903,
      "overlap_obb": 0.250641836890237,
      "overlap_geometry": 0.0014772159949665233,
      "center_difference": [
        -0.06816595050078433,
        0.4582595972344774,
        -0.7399589607430466
      ],
      "log_obb_volume_ratio": 0.6696109146892453,
      "log_geom_volume_ratio": 1.2772982173950864,
      "source": "ceiling:6",
      "target": "wall:4"
    },
    {
      "type": "touching",
      "weight": 0.23788265262473662,
      "weight_inv": 4.203753358919848,
      "overlap_obb": 0.47564904287949905,
      "overlap_geometry": 0.00011626236997421711,
      "center_difference": [
        -0.25129756721687313,
        0.24205703039229098,
        -0.3386085310645697
      ],
      "log_obb_volume_ratio": 7.679953831008806,
      "log_geom_volume_ratio": 1.05113267746536,
      "source": "wall:7",
      "target": "table:16"
    },
    {
      "type": "touching",
      "weight": 0.08100654958308107,
      "weight_inv": 12.34468083317622,
      "overlap_obb": 0.1618831588703086,
      "overlap_geometry": 0.00012994029585353676,
      "center_difference": [
        -0.06928031883086441,
        1.9328260501996863,
        -0.6869799590176391
      ],
      "log_obb_volume_ratio": -0.13643757114522562,
      "log_geom_volume_ratio": 1.4590151204002326,
      "source": "cabinet:8",
      "target": "floor:1"
    },
    {
      "type": "touching",
      "weight": 0.04398057062542191,
      "weight_inv": 22.73731299479716,
      "overlap_obb": 0.08795430228790417,
      "overlap_geometry": 6.83896293965983e-06,
      "center_difference": [
        -1.656927402953627,
        1.0434935692123872,
        0.6072655861967071
      ],
      "log_obb_volume_ratio": -0.632400874323575,
      "log_geom_volume_ratio": 1.226955199507892,
      "source": "cabinet:8",
      "target": "wall:3"
    },
    {
      "type": "touching",
      "weight": 0.052333295956069566,
      "weight_inv": 19.108293902211617,
      "overlap_obb": 0.10452297369040628,
      "overlap_geometry": 0.00014361822173285642,
      "center_difference": [
        -0.8548008922471301,
        1.859079352276996,
        -0.732657368325971
      ],
      "log_obb_volume_ratio": -0.8018239590685038,
      "log_geom_volume_ratio": 1.5384149817520862,
      "source": "door:9",
      "target": "floor:1"
    },
    {
      "type": "weak_touching",
      "weight": 0.028654771514275833,
      "weight_inv": 34.89820184054859,
      "overlap_obb": 0.057309543028551665,
      "overlap_geometry": 0.0,
      "center_difference": [
        -0.7855205734162657,
        -0.0737466979226904,
        -0.04567740930833186
      ],
      "log_obb_volume_ratio": 5.876856003358736,
      "log_geom_volume_ratio": 1.0544201771740878,
      "source": "door:9",
      "target": "cabinet:8"
    },
    {
      "type": "touching",
      "weight": 0.02142569020936279,
      "weight_inv": 46.672942165616256,
      "overlap_obb": 0.04284454145578592,
      "overlap_geometry": 6.83896293965983e-06,
      "center_difference": [
        -0.5274382607436606,
        -1.1144875427396315,
        -1.4372527954433563
      ],
      "log_obb_volume_ratio": 0.888813559468604,
      "log_geom_volume_ratio": 1.285266798991814,
      "source": "wall:10",
      "target": "floor:1"
    },
    {
      "type": "weak_touching",
      "weight": 0.24618556695812535,
      "weight_inv": 4.0619765502747525,
      "overlap_obb": 0.4923711339162507,
      "overlap_geometry": 0.0,
      "center_difference": [
        -1.2127187378793773,
        0.8917669336533744,
        0.13208470292141172
      ],
      "log_obb_volume_ratio": -0.05958113581521217,
      "log_geom_volume_ratio": 1.2350521449011873,
      "source": "window:11",
      "target": "wall:10"
    },
    {
      "type": "weak_touching",
      "weight": 0.22556277811928377,
      "weight_inv": 4.433355575498244,
      "overlap_obb": 0.45112555623856754,
      "overlap_geometry": 0.0,
      "center_difference": [
        0.13330277213883984,
        -0.5098863744772424,
        0.09590267747863691
      ],
      "log_obb_volume_ratio": 0.024563824197236378,
      "log_geom_volume_ratio": 1.0894667901594692,
      "source": "window:12",
      "target": "wall:10"
    },
    {
      "type": "weak_touching",
      "weight": 0.05573029088290305,
      "weight_inv": 17.943563260797195,
      "overlap_obb": 0.1114605817658061,
      "overlap_geometry": 0.0,
      "center_difference": [
        -1.43813681116498,
        0.32971045259777654,
        0.9257219826233911
      ],
      "log_obb_volume_ratio": 0.01426470469805277,
      "log_geom_volume_ratio": 1.355124207228726,
      "source": "table:13",
      "target": "wall:4"
    },
    {
      "type": "weak_touching",
      "weight": 0.10110362998048397,
      "weight_inv": 9.890841705614625,
      "overlap_obb": 0.20220725996096794,
      "overlap_geometry": 0.0,
      "center_difference": [
        0.4487795844749487,
        0.11864794646913879,
        0.6335136649639961
      ],
      "log_obb_volume_ratio": 0.013627405709292275,
      "log_geom_volume_ratio": 1.1717889096155238,
      "source": "table:13",
      "target": "wall:10"
    },
    {
      "type": "touching",
      "weight": 0.2043185848340593,
      "weight_inv": 4.894317376033935,
      "overlap_obb": 0.40832257737289424,
      "overlap_geometry": 0.00031459229522435217,
      "center_difference": [
        0.8428066480855658,
        1.007533976996104,
        0.5925771548328942
      ],
      "log_obb_volume_ratio": 0.24007991878515614,
      "log_geom_volume_ratio": 1.2112313642023582,
      "source": "shelf:14",
      "target": "wall:4"
    },
    {
      "type": "touching",
      "weight": 0.12160575877587057,
      "weight_inv": 8.223294768819972,
      "overlap_obb": 0.2430815772558876,
      "overlap_geometry": 0.00012994029585353676,
      "center_difference": [
        0.9109725985863502,
        0.5492743797616266,
        1.3325361155759405
      ],
      "log_obb_volume_ratio": 0.3585364478363873,
      "log_geom_volume_ratio": 0.9482760937947096,
      "source": "shelf:14",
      "target": "ceiling:6"
    },
    {
      "type": "part_within",
      "weight": 0.4246665527667105,
      "weight_inv": 2.354788700652268,
      "overlap_obb": 0.849333105533421,
      "overlap_geometry": 0.0,
      "center_difference": [
        0.08181524418556374,
        0.18092910181539512,
        1.2559045077217528
      ],
      "log_obb_volume_ratio": -1.1858024053837704,
      "log_geom_volume_ratio": 1.6567577972367484,
      "source": "object:15",
      "target": "wall:4"
    },
    {
      "type": "touching",
      "weight": 0.11153959622725639,
      "weight_inv": 8.965426035455156,
      "overlap_obb": 0.22301080282511618,
      "overlap_geometry": 6.83896293965983e-05,
      "center_difference": [
        -1.4100955264041366,
        0.6329641956147656,
        -0.6970537288000683
      ],
      "log_obb_volume_ratio": -0.043052170240049384,
      "log_geom_volume_ratio": 1.5852724606281448,
      "source": "table:16",
      "target": "floor:1"
    },
    {
      "type": "touching",
      "weight": 0.23187655141184788,
      "weight_inv": 4.3126396089264265,
      "overlap_obb": 0.4636300014907819,
      "overlap_geometry": 0.00012310133291387694,
      "center_difference": [
        -0.807659436802664,
        1.190616426885895,
        0.9494298367935943
      ],
      "log_obb_volume_ratio": -1.1892699092444374,
      "log_geom_volume_ratio": 1.45763350420411,
      "source": "box:17",
      "target": "wall:10"
    },
    {
      "type": "touching",
      "weight": 0.13535370741805983,
      "weight_inv": 7.388050309633211,
      "overlap_obb": 0.27061850831790407,
      "overlap_geometry": 8.89065182155778e-05,
      "center_difference": [
        -0.34455280163306634,
        -0.6214606920580006,
        -0.4033836179498016
      ],
      "log_obb_volume_ratio": -0.2788596105591969,
      "log_geom_volume_ratio": 1.4441368998934514,
      "source": "curtain:18",
      "target": "floor:1"
    },
    {
      "type": "touching",
      "weight": 0.17335595425154246,
      "weight_inv": 5.768477952300287,
      "overlap_obb": 0.3466640357625073,
      "overlap_geometry": 4.787274057761881e-05,
      "center_difference": [
        -0.2658941253643544,
        0.3743789042124921,
        0.4003555125295585
      ],
      "log_obb_volume_ratio": -23.022991827297346,
      "log_geom_volume_ratio": 0.9588831625023757,
      "source": "curtain:18",
      "target": "table:13"
    },
    {
      "type": "touching",
      "weight": 0.09388902104193038,
      "weight_inv": 10.65087258235875,
      "overlap_obb": 0.18766177971388653,
      "overlap_geometry": 0.00011626236997421711,
      "center_difference": [
        0.43813967064642323,
        -0.9751444609330215,
        -0.6185267839385461
      ],
      "log_obb_volume_ratio": -0.667519729075018,
      "log_geom_volume_ratio": 1.8709392682668717,
      "source": "chair:19",
      "target": "floor:1"
    },
    {
      "type": "weak_touching",
      "weight": 0.1446696319780384,
      "weight_inv": 6.912300711125091,
      "overlap_obb": 0.2893392639560768,
      "overlap_geometry": 0.0,
      "center_difference": [
        0.5167983469151352,
        0.020695135337471138,
        0.18521234654081398
      ],
      "log_obb_volume_ratio": -55.11124840286423,
      "log_geom_volume_ratio": 1.2422729192349986,
      "source": "chair:19",
      "target": "table:13"
    },
    {
      "type": "part_within",
      "weight": 0.36370670920575965,
      "weight_inv": 2.7494681145248556,
      "overlap_obb": 0.7274134184115193,
      "overlap_geometry": 0.0,
      "center_difference": [
        -0.9073332453614142,
        -0.5593580914707674,
        0.7044651313665398
      ],
      "log_obb_volume_ratio": -2.7066902688392624,
      "log_geom_volume_ratio": 2.218272484426939,
      "source": "object:21",
      "target": "wall:4"
    },
    {
      "type": "touching",
      "weight": 0.24503890494849662,
      "weight_inv": 4.0809846102200975,
      "overlap_obb": 0.49003677611935526,
      "overlap_geometry": 4.103377763795898e-05,
      "center_difference": [
        0.9795831502785145,
        -0.7704205975994052,
        0.4122568137071449
      ],
      "log_obb_volume_ratio": -2.5857644587553983,
      "log_geom_volume_ratio": 1.9181615101338296,
      "source": "object:21",
      "target": "wall:10"
    },
    {
      "type": "part_within",
      "weight": 0.33761981561828935,
      "weight_inv": 2.961911457029504,
      "overlap_obb": 0.6752327922736391,
      "overlap_geometry": 6.83896293965983e-06,
      "center_difference": [
        0.5308035658035658,
        -0.889068544068544,
        -0.22125685125685124
      ],
      "log_obb_volume_ratio": -189.74737480606552,
      "log_geom_volume_ratio": 1.6369514119767512,
      "source": "object:21",
      "target": "table:13"
    },
    {
      "type": "weak_touching",
      "weight": 0.20419036827041412,
      "weight_inv": 4.897390648101855,
      "overlap_obb": 0.40838073654082824,
      "overlap_geometry": 0.0,
      "center_difference": [
        0.7004019404019405,
        -0.32599792099792113,
        -0.1711365211365211
      ],
      "log_obb_volume_ratio": -312.8350115298652,
      "log_geom_volume_ratio": 1.9487774800892195,
      "source": "box:22",
      "target": "table:13"
    },
    {
      "type": "weak_touching",
      "weight": 0.22739361844335584,
      "weight_inv": 4.397660791211262,
      "overlap_obb": 0.4547872368867117,
      "overlap_geometry": 0.0,
      "center_difference": [
        0.18360359348680533,
        -0.34669305633539227,
        -0.3563488676773351
      ],
      "log_obb_volume_ratio": 5.67642760046072,
      "log_geom_volume_ratio": 1.5687192805340167,
      "source": "box:22",
      "target": "chair:19"
    },
    {
      "type": "within",
      "weight": 0.49999972222237654,
      "weight_inv": 2.000001111111111,
      "overlap_obb": 0.9999994444447531,
      "overlap_geometry": 0.0,
      "center_difference": [
        0.4050790534123866,
        -0.7409646826313492,
        -0.11285541952208611
      ],
      "log_obb_volume_ratio": -388.2477277449444,
      "log_geom_volume_ratio": 2.3872895548230475,
      "source": "-:23",
      "target": "table:13"
    },
    {
      "type": "within",
      "weight": 0.4999941953558575,
      "weight_inv": 2.0000232188461244,
      "overlap_obb": 0.999988390711715,
      "overlap_geometry": 0.0,
      "center_difference": [
        0.12573897450186097,
        -0.3380386294303819,
        -0.10672203527873625
      ],
      "log_obb_volume_ratio": -257.3412612577096,
      "log_geom_volume_ratio": 1.8778892742485347,
      "source": "box:24",
      "target": "table:13"
    },
    {
      "type": "weak_touching",
      "weight": 0.21825931278197297,
      "weight_inv": 4.58170598657999,
      "overlap_obb": 0.43651862556394594,
      "overlap_geometry": 0.0,
      "center_difference": [
        0.117194358510148,
        -0.3129712984976143,
        -0.29362333257070095
      ],
      "log_obb_volume_ratio": -332.23187943622634,
      "log_geom_volume_ratio": 2.079063817915764,
      "source": "object:25",
      "target": "table:13"
    },
    {
      "type": "within",
      "weight": 0.49923000961042824,
      "weight_inv": 2.0030847119554074,
      "overlap_obb": 0.9984463412949771,
      "overlap_geometry": 1.367792587931966e-05,
      "center_difference": [
        0.45871297719123805,
        -0.4185787459700503,
        -0.12363373406851658
      ],
      "log_obb_volume_ratio": -374.4267405670621,
      "log_geom_volume_ratio": 2.3458823342522304,
      "source": "-:26",
      "target": "table:13"
    },
    {
      "type": "within",
      "weight": 0.48141316770386117,
      "weight_inv": 2.077217797696686,
      "overlap_obb": 0.9628194964447827,
      "overlap_geometry": 6.83896293965983e-06,
      "center_difference": [
        -0.25021547921547926,
        0.0012222662222660663,
        -0.10948328548328534
      ],
      "log_obb_volume_ratio": -198.43510493077167,
      "log_geom_volume_ratio": 1.5884277559327054,
      "source": "box:27",
      "target": "table:13"
    },
    {
      "type": "part_within",
      "weight": 0.2789860364048121,
      "weight_inv": 3.584408785782339,
      "overlap_obb": 0.5579720728096242,
      "overlap_geometry": 0.0,
      "center_difference": [
        -0.2413232828154186,
        0.42955707675326904,
        0.4654140028018341
      ],
      "log_obb_volume_ratio": -2.4946116419512405,
      "log_geom_volume_ratio": 1.909827527898149,
      "source": "-:28",
      "target": "wall:10"
    },
    {
      "type": "part_within",
      "weight": 0.354116042299813,
      "weight_inv": 2.8239330630306436,
      "overlap_obb": 0.7081910508219881,
      "overlap_geometry": 4.103377763795898e-05,
      "center_difference": [
        -0.6901028672903673,
        0.31090913028413025,
        -0.16809966216216204
      ],
      "log_obb_volume_ratio": -183.05844084837156,
      "log_geom_volume_ratio": 1.629839224647367,
      "source": "-:28",
      "target": "table:13"
    },
    {
      "type": "within",
      "weight": 0.45861816617193324,
      "weight_inv": 2.1804631254513063,
      "overlap_obb": 0.9172363323438665,
      "overlap_geometry": 0.0,
      "center_difference": [
        -1.0136536232322317,
        0.8886692269698713,
        0.5070475571280253
      ],
      "log_obb_volume_ratio": -2.5963323956721016,
      "log_geom_volume_ratio": 1.9998078691805175,
      "source": "window:29",
      "target": "wall:10"
    },
    {
      "type": "within",
      "weight": 0.4875173098624858,
      "weight_inv": 2.05120921815488,
      "overlap_obb": 0.9750346197249716,
      "overlap_geometry": 0.0,
      "center_difference": [
        0.1990651146471456,
        -0.0030977066835031764,
        0.3749628542066136
      ],
      "log_obb_volume_ratio": 43.576416598107386,
      "log_geom_volume_ratio": 1.6192092596547947,
      "source": "window:29",
      "target": "window:11"
    },
    {
      "type": "part_within",
      "weight": 0.39711503426563644,
      "weight_inv": 2.5181620279102415,
      "overlap_obb": 0.7942300685312729,
      "overlap_geometry": 0.0,
      "center_difference": [
        0.28286329953376743,
        -0.4023515704432412,
        0.5167137753840236
      ],
      "log_obb_volume_ratio": -2.617490289975522,
      "log_geom_volume_ratio": 1.963333407862087,
      "source": "window:30",
      "target": "wall:10"
    },
    {
      "type": "within",
      "weight": 0.4546391308996102,
      "weight_inv": 2.199546699865595,
      "overlap_obb": 0.9091961942439445,
      "overlap_geometry": 8.206755527591796e-05,
      "center_difference": [
        0.1495605273949276,
        0.10753480403400117,
        0.42081109790538673
      ],
      "log_obb_volume_ratio": -106.55874545259161,
      "log_geom_volume_ratio": 1.802104869644266,
      "source": "window:30",
      "target": "window:12"
    },
    {
      "type": "part_within",
      "weight": 0.3137988143010838,
      "weight_inv": 3.1867551897137494,
      "overlap_obb": 0.6275976286021676,
      "overlap_geometry": 0.0,
      "center_difference": [
        -0.8255602333648692,
        0.7179046042257966,
        0.4431811731315044
      ],
      "log_obb_volume_ratio": -2.9280709655024615,
      "log_geom_volume_ratio": 2.324788785032306,
      "source": "object:31",
      "target": "wall:10"
    },
    {
      "type": "within",
      "weight": 0.49999998348139735,
      "weight_inv": 2.0000000660744126,
      "overlap_obb": 0.9999999669627947,
      "overlap_geometry": 0.0,
      "center_difference": [
        0.38715850451450806,
        -0.1738623294275779,
        0.3110964702100927
      ],
      "log_obb_volume_ratio": 49.14426228099651,
      "log_geom_volume_ratio": 1.882340591553165,
      "source": "object:31",
      "target": "window:11"
    },
    {
      "type": "part_within",
      "weight": 0.4086983110422702,
      "weight_inv": 2.4467925924376366,
      "overlap_obb": 0.8172051311222299,
      "overlap_geometry": 0.00019149096231047523,
      "center_difference": [
        0.4208605859165012,
        0.3678705548306397,
        0.27249120818983896
      ],
      "log_obb_volume_ratio": 22.610024909028102,
      "log_geom_volume_ratio": 1.205200169094189,
      "source": "-:36",
      "target": "table:16"
    },
    {
      "type": "part_within",
      "weight": 0.30337713170432085,
      "weight_inv": 3.2962273536643023,
      "overlap_obb": 0.6067269075568831,
      "overlap_geometry": 2.735585175863932e-05,
      "center_difference": [
        -0.11523912521028579,
        -0.2957101658255228,
        0.4030978130257151
      ],
      "log_obb_volume_ratio": 6.466080432814868,
      "log_geom_volume_ratio": 1.4579332600129002,
      "source": "sink:37",
      "target": "wall:7"
    },
    {
      "type": "within",
      "weight": 0.4965278552960645,
      "weight_inv": 2.0139856995610654,
      "overlap_obb": 0.9929873209627325,
      "overlap_geometry": 6.83896293965983e-05,
      "center_difference": [
        -0.3665366924271589,
        -0.0536531354332318,
        0.06448928196114545
      ],
      "log_obb_volume_ratio": 49.65919919160763,
      "log_geom_volume_ratio": 1.5324812911631605,
      "source": "sink:37",
      "target": "table:16"
    },
    {
      "type": "part_within",
      "weight": 0.39566792836498604,
      "weight_inv": 2.5273718901915765,
      "overlap_obb": 0.7913358567299721,
      "overlap_geometry": 0.0,
      "center_difference": [
        0.20227937425120546,
        0.03188916977649359,
        0.7912806181820267
      ],
      "log_obb_volume_ratio": -2.927427074976813,
      "log_geom_volume_ratio": 2.2835003449118143,
      "source": "window:38",
      "target": "wall:4"
    },
    {
      "type": "part_within",
      "weight": 0.3896075041530569,
      "weight_inv": 2.566685675559142,
      "overlap_obb": 0.7786610523080013,
      "overlap_geometry": 0.0005539559981124463,
      "center_difference": [
        -0.06800301974214995,
        0.0016611059219753255,
        0.5394156363721582
      ],
      "log_obb_volume_ratio": 3.6424972712662136,
      "log_geom_volume_ratio": 1.533076895361201,
      "source": "window:38",
      "target": "window:5"
    },
    {
      "type": "part_within",
      "weight": 0.42546239446003725,
      "weight_inv": 2.35038398932794,
      "overlap_obb": 0.8509247889200745,
      "overlap_geometry": 0.0,
      "center_difference": [
        0.3511342451956285,
        0.16849056451221678,
        0.6976528170169121
      ],
      "log_obb_volume_ratio": -3.944822815335565,
      "log_geom_volume_ratio": 2.707821253269829,
      "source": "plant:39",
      "target": "wall:4"
    },
    {
      "type": "within",
      "weight": 0.4979948473153864,
      "weight_inv": 2.008052905348009,
      "overlap_obb": 0.9959828556678332,
      "overlap_geometry": 6.83896293965983e-06,
      "center_difference": [
        0.08085185120227312,
        0.13826250065769852,
        0.4457878352070435
      ],
      "log_obb_volume_ratio": 4.9084079543133665,
      "log_geom_volume_ratio": 1.8179538310147718,
      "source": "plant:39",
      "target": "window:5"
    },
    {
      "type": "weak_touching",
      "weight": 0.12925377568232904,
      "weight_inv": 7.736717900278059,
      "overlap_obb": 0.2585075513646581,
      "overlap_geometry": 0.0,
      "center_difference": [
        0.6051188993830892,
        -1.1940158410919457,
        0.19563629219751055
      ],
      "log_obb_volume_ratio": -5.089360876030249,
      "log_geom_volume_ratio": 2.3112145817280445,
      "source": "-:40",
      "target": "sofa:2"
    },
    {
      "type": "weak_touching",
      "weight": 0.14027582447709497,
      "weight_inv": 7.128812136572297,
      "overlap_obb": 0.28055164895418994,
      "overlap_geometry": 0.0,
      "center_difference": [
        0.3334792087952487,
        0.6485169821791839,
        1.3594639489591585
      ],
      "log_obb_volume_ratio": -2.888176789783977,
      "log_geom_volume_ratio": 2.3432383886074404,
      "source": "-:40",
      "target": "wall:4"
    },
    {
      "type": "part_within",
      "weight": 0.257641079209511,
      "weight_inv": 3.8813686197409947,
      "overlap_obb": 0.5152684804931427,
      "overlap_geometry": 1.367792587931966e-05,
      "center_difference": [
        -0.5093274392903171,
        -0.35901699481692023,
        0.7668867941262644
      ],
      "log_obb_volume_ratio": -12.030064007013273,
      "log_geom_volume_ratio": 1.9345919019778288,
      "source": "-:40",
      "target": "shelf:14"
    },
    {
      "type": "touching",
      "weight": 0.14626248944962236,
      "weight_inv": 6.837022969887526,
      "overlap_obb": 0.29242239445514984,
      "overlap_geometry": 0.00010258444409489744,
      "center_difference": [
        0.251663964609685,
        0.46758788036378873,
        0.10355944123740568
      ],
      "log_obb_volume_ratio": 2.4356307397177646,
      "log_geom_volume_ratio": 1.4143518096101015,
      "source": "-:40",
      "target": "object:15"
    },
    {
      "type": "weak_touching",
      "weight": 0.13293273004597267,
      "weight_inv": 7.522601842707706,
      "overlap_obb": 0.26586546009194534,
      "overlap_geometry": 0.0,
      "center_difference": [
        -0.06248763599234808,
        -0.1605030572605537,
        0.11419521870268878
      ],
      "log_obb_volume_ratio": 1.000662341286039,
      "log_geom_volume_ratio": 1.0241801057827338,
      "source": "-:40",
      "target": "-:41"
    },
    {
      "type": "touching",
      "weight": 0.14589702265873764,
      "weight_inv": 6.854149466360689,
      "overlap_obb": 0.291739333613958,
      "overlap_geometry": 5.471170351727864e-05,
      "center_difference": [
        0.1855095011178607,
        0.09820375567674655,
        -0.2520731772152254
      ],
      "log_obb_volume_ratio": 1.1604506306642888,
      "log_geom_volume_ratio": 0.9906522253701816,
      "source": "-:40",
      "target": "box:43"
    },
    {
      "type": "part_within",
      "weight": 0.27790233171103296,
      "weight_inv": 3.5983865045069687,
      "overlap_obb": 0.5558046634220659,
      "overlap_geometry": 0.0,
      "center_difference": [
        0.6676065353754372,
        -1.0335127838313922,
        0.08144107349482177
      ],
      "log_obb_volume_ratio": -5.085992213406837,
      "log_geom_volume_ratio": 2.2566485803409444,
      "source": "-:41",
      "target": "sofa:2"
    },
    {
      "type": "part_within",
      "weight": 0.36773462063100215,
      "weight_inv": 2.719352336976276,
      "overlap_obb": 0.7353871737067283,
      "overlap_geometry": 8.206755527591796e-05,
      "center_difference": [
        -0.446839803297969,
        -0.19851393755636654,
        0.6526915754235756
      ],
      "log_obb_volume_ratio": -12.022101272995226,
      "log_geom_volume_ratio": 1.8889176728338315,
      "source": "-:41",
      "target": "shelf:14"
    },
    {
      "type": "weak_touching",
      "weight": 0.22889019691401605,
      "weight_inv": 4.368907071960168,
      "overlap_obb": 0.4577803938280321,
      "overlap_geometry": 0.0,
      "center_difference": [
        0.2620138471856781,
        0.5270766341639581,
        1.4717752050766137
      ],
      "log_obb_volume_ratio": -4.436257139939164,
      "log_geom_volume_ratio": 2.9635523601445666,
      "source": "-:42",
      "target": "wall:4"
    },
    {
      "type": "part_within",
      "weight": 0.43237079558504543,
      "weight_inv": 2.312829659660268,
      "overlap_obb": 0.8647347522071512,
      "overlap_geometry": 6.83896293965983e-06,
      "center_difference": [
        0.18019860300011437,
        0.346147532348563,
        0.21587069735486097
      ],
      "log_obb_volume_ratio": 3.7411436507445974,
      "log_geom_volume_ratio": 1.7887662065555858,
      "source": "-:42",
      "target": "object:15"
    },
    {
      "type": "part_within",
      "weight": 0.28105455966968734,
      "weight_inv": 3.5580280255024563,
      "overlap_obb": 0.5621022803764351,
      "overlap_geometry": 6.83896293965983e-06,
      "center_difference": [
        -0.07146536160957062,
        -0.12144034801522574,
        0.1123112561174553
      ],
      "log_obb_volume_ratio": 1.5360060906351152,
      "log_geom_volume_ratio": 1.2647250807058394,
      "source": "-:42",
      "target": "-:40"
    },
    {
      "type": "part_within",
      "weight": 0.2915279841087662,
      "weight_inv": 3.430202431705184,
      "overlap_obb": 0.5830559682175324,
      "overlap_geometry": 0.0,
      "center_difference": [
        0.11404413950829007,
        -0.02323659233847919,
        -0.13976192109777008
      ],
      "log_obb_volume_ratio": 1.7824592365817082,
      "log_geom_volume_ratio": 1.2529027156827224,
      "source": "-:42",
      "target": "box:43"
    },
    {
      "type": "part_within",
      "weight": 0.36115285017894416,
      "weight_inv": 2.768910724377558,
      "overlap_obb": 0.7222783445061297,
      "overlap_geometry": 2.735585175863932e-05,
      "center_difference": [
        1.5074478425736562,
        -0.7752368223658319,
        -0.11792398692836725
      ],
      "log_obb_volume_ratio": -2.1132855153172496,
      "log_geom_volume_ratio": 2.628807730056635,
      "source": "box:43",
      "target": "floor:1"
    }
  ]
}