{
  "directed": true,
  "multigraph": false,
  "graph": {},
  "nodes": [
    {
      "id": "floor:1",
      "centrality": 0.09835812426831919
    },
    {
      "id": "wall:2",
      "centrality": 0.42966917770434415
    },
    {
      "id": "tv:3",
      "centrality": 0.0
    },
    {
      "id": "wall:4",
      "centrality": 0.0
    },
    {
      "id": "wall:5",
      "centrality": 0.009015930705029656
    },
    {
      "id": "wall:6",
      "centrality": 0.0
    },
    {
      "id": "cabinet:7",
      "centrality": 0.3676804737671664
    },
    {
      "id": "curtain:8",
      "centrality": 0.24686228222789144
    },
    {
      "id": "ceiling:9",
      "centrality": 0.17683192438399573
    },
    {
      "id": "blanket:10",
      "centrality": 0.0
    },
    {
      "id": "blanket:11",
      "centrality": 0.0
    },
    {
      "id": "pillow:12",
      "centrality": 0.0
    },
    {
      "id": "pillow:13",
      "centrality": 0.0
    },
    {
      "id": "pillow:14",
      "centrality": 0.0
    },
    {
      "id": "pillow:15",
      "centrality": 0.0
    },
    {
      "id": "pillow:16",
      "centrality": 0.0
    },
    {
      "id": "pillow:17",
      "centrality": 0.0
    },
    {
      "id": "bed:18",
      "centrality": 2.0
    },
    {
      "id": "table:19",
      "centrality": 0.0
    },
    {
      "id": "table:20",
      "centrality": 0.0
    },
    {
      "id": "table:21",
      "centrality": 0.0
    },
    {
      "id": "lamp:22",
      "centrality": 0.0
    },
    {
      "id": "chair:23",
      "centrality": 0.17523217864300636
    },
    {
      "id": "object:24",
      "centrality": 0.0
    },
    {
      "id": "door:26",
      "centrality": 0.007060700787468489
    },
    {
      "id": "shelf:33",
      "centrality": 0.0
    },
    {
      "id": "window:34",
      "centrality": 0.0
    },
    {
      "id": "-:36",
      "centrality": 0.0
    }
  ],
  "links": [
    {
      "type": "touching",
      "weight": 0.11088115219915952,
      "weight_inv": 9.018665302141224,
      "overlap_obb": 0.2215321938241326,
      "overlap_geometry": 0.000230110574186438,
      "center_difference": [
        0.7599853666842766,
        0.7945376352291875,
        0.47657348958891244
      ],
      "log_obb_volume_ratio": 0.8115250035096608,
      "log_geom_volume_ratio": 0.8059176104445377,
      "source": "floor:1",
      "target": "bed:18"
    },
    {
      "type": "touching",
      "weight": 0.04853089158957409,
      "weight_inv": 20.60543227717725,
      "overlap_obb": 0.0966661544726522,
      "overlap_geometry": 0.00039562870649598116,
      "center_difference": [
        0.7417760885924176,
        1.1165923489063427,
        1.239691326260441
      ],
      "log_obb_volume_ratio": 0.9846010337382164,
      "log_geom_volume_ratio": 0.8354979924802031,
      "source": "wall:2",
      "target": "ceiling:9"
    },
    {
      "type": "within",
      "weight": 0.5000100847795855,
      "weight_inv": 1.9999596616952637,
      "overlap_obb": 0.9999999844210845,
      "overlap_geometry": 2.018513808652965e-05,
      "center_difference": [
        0.3979926029578047,
        -0.6440925501158856,
        -0.0860739776534985
      ],
      "log_obb_volume_ratio": -1.545319451321294,
      "log_geom_volume_ratio": 3.7487027501818577,
      "source": "tv:3",
      "target": "wall:2"
    },
    {
      "type": "touching",
      "weight": 0.028375923522055268,
      "weight_inv": 35.241143754237534,
      "overlap_obb": 0.056687254602233644,
      "overlap_geometry": 6.459244187689488e-05,
      "center_difference": [
        -1.3876528815073792,
        1.4605944232524908,
        -1.0963913992218226
      ],
      "log_obb_volume_ratio": -0.15036978144261026,
      "log_geom_volume_ratio": 1.3514785298626575,
      "source": "wall:4",
      "target": "floor:1"
    },
    {
      "type": "weak_touching",
      "weight": 0.024686267080126643,
      "weight_inv": 40.508352143894484,
      "overlap_obb": 0.049372534160253286,
      "overlap_geometry": 0.0,
      "center_difference": [
        -0.020359463698170877,
        1.2952658284827743,
        0.23920257881872747
      ],
      "log_obb_volume_ratio": -0.4055064237312747,
      "log_geom_volume_ratio": 0.9800102617758308,
      "source": "wall:4",
      "target": "wall:5"
    },
    {
      "type": "weak_touching",
      "weight": 0.016258395351911592,
      "weight_inv": 61.50668490678721,
      "overlap_obb": 0.032516790703823184,
      "overlap_geometry": 0.0,
      "center_difference": [
        -1.222657359063815,
        1.987093626307336,
        1.3475692571619928
      ],
      "log_obb_volume_ratio": -0.13962788209749896,
      "log_geom_volume_ratio": 1.588490497918803,
      "source": "wall:4",
      "target": "ceiling:9"
    },
    {
      "type": "touching",
      "weight": 0.01933270686242861,
      "weight_inv": 51.72581403711297,
      "overlap_obb": 0.03812445202413822,
      "overlap_geometry": 0.0005409617007189946,
      "center_difference": [
        0.15374225327656543,
        -1.1699502659795775,
        -0.012855052333724915
      ],
      "log_obb_volume_ratio": -1.1207612988932203,
      "log_geom_volume_ratio": 0.7993161440732365,
      "source": "wall:4",
      "target": "door:26"
    },
    {
      "type": "touching",
      "weight": 0.06947276990143099,
      "weight_inv": 14.394128828011537,
      "overlap_obb": 0.13886883627813318,
      "overlap_geometry": 7.670352472881267e-05,
      "center_difference": [
        -1.2022978953656442,
        0.6918277978245618,
        1.1083666783432653
      ],
      "log_obb_volume_ratio": 0.3443296429504383,
      "log_geom_volume_ratio": 1.620891698664842,
      "source": "wall:5",
      "target": "ceiling:9"
    },
    {
      "type": "weak_touching",
      "weight": 0.1351688789977816,
      "weight_inv": 7.398152647373898,
      "overlap_obb": 0.2703377579955632,
      "overlap_geometry": 0.0,
      "center_difference": [
        -0.6073080511249318,
        0.959866229998904,
        -0.8590204884516376
      ],
      "log_obb_volume_ratio": 0.30092948045091533,
      "log_geom_volume_ratio": 1.1113968800493548,
      "source": "wall:5",
      "target": "bed:18"
    },
    {
      "type": "weak_touching",
      "weight": 0.06079596772683937,
      "weight_inv": 16.44845928751511,
      "overlap_obb": 0.12159193545367875,
      "overlap_geometry": 0.0,
      "center_difference": [
        -1.121024090435095,
        1.268750680970397,
        -0.5217681417227129
      ],
      "log_obb_volume_ratio": -0.07213812884750749,
      "log_geom_volume_ratio": 1.1872266997312042,
      "source": "wall:6",
      "target": "cabinet:7"
    },
    {
      "type": "weak_touching",
      "weight": 0.04615593754831679,
      "weight_inv": 21.665684917637815,
      "overlap_obb": 0.09231187509663358,
      "overlap_geometry": 0.0,
      "center_difference": [
        -1.2739784306501323,
        -0.8660075024185653,
        0.6176202379130161
      ],
      "log_obb_volume_ratio": -0.025701637647305868,
      "log_geom_volume_ratio": 1.9913862646611762,
      "source": "wall:6",
      "target": "ceiling:9"
    },
    {
      "type": "weak_touching",
      "weight": 0.047875869790065605,
      "weight_inv": 20.887348979454014,
      "overlap_obb": 0.09575173958013121,
      "overlap_geometry": 0.0,
      "center_difference": [
        -0.6789885864094198,
        -0.5979690702442231,
        -1.3497669288818868
      ],
      "log_obb_volume_ratio": -0.022462139470968243,
      "log_geom_volume_ratio": 1.3654339048936086,
      "source": "wall:6",
      "target": "bed:18"
    },
    {
      "type": "touching",
      "weight": 0.029643977768852144,
      "weight_inv": 33.733664483135975,
      "overlap_obb": 0.059211252012975474,
      "overlap_geometry": 7.670352472881267e-05,
      "center_difference": [
        -0.3179498626586016,
        -2.6612573864438076,
        -1.3045722767480865
      ],
      "log_obb_volume_ratio": 0.3836934108273528,
      "log_geom_volume_ratio": 1.4270736319901125,
      "source": "cabinet:7",
      "target": "floor:1"
    },
    {
      "type": "touching",
      "weight": 0.025392878018421158,
      "weight_inv": 39.38112092983529,
      "overlap_obb": 0.05069290440164428,
      "overlap_geometry": 9.285163519803639e-05,
      "center_difference": [
        -1.4632010273221239,
        -0.36159980200849473,
        -0.056098423479586074
      ],
      "log_obb_volume_ratio": 0.7628766133381099,
      "log_geom_volume_ratio": 1.5143582098696386,
      "source": "cabinet:7",
      "target": "curtain:8"
    },
    {
      "type": "weak_touching",
      "weight": 0.031052830697151958,
      "weight_inv": 32.20318333464253,
      "overlap_obb": 0.062105661394303915,
      "overlap_geometry": 0.0,
      "center_difference": [
        -0.15295434021503743,
        -2.1347581833889624,
        1.139388379635729
      ],
      "log_obb_volume_ratio": 0.3562836749153344,
      "log_geom_volume_ratio": 1.6773428908834673,
      "source": "cabinet:7",
      "target": "ceiling:9"
    },
    {
      "type": "touching",
      "weight": 0.04781416060272063,
      "weight_inv": 20.914306293251123,
      "overlap_obb": 0.09562024715020666,
      "overlap_geometry": 8.07405523461186e-06,
      "center_difference": [
        0.44203550402567504,
        -1.86671975121462,
        -0.827998787159174
      ],
      "log_obb_volume_ratio": 0.3113767965683012,
      "log_geom_volume_ratio": 1.150103771421879,
      "source": "cabinet:7",
      "target": "bed:18"
    },
    {
      "type": "touching",
      "weight": 0.035590974767209314,
      "weight_inv": 28.09701073209493,
      "overlap_obb": 0.0709639500430841,
      "overlap_geometry": 0.0002179994913345202,
      "center_difference": [
        1.1452511646635222,
        -2.299657584435313,
        -1.2484738532685005
      ],
      "log_obb_volume_ratio": 0.5029560535987991,
      "log_geom_volume_ratio": 0.9423620004100351,
      "source": "curtain:8",
      "target": "floor:1"
    },
    {
      "type": "touching",
      "weight": 0.01898131368716281,
      "weight_inv": 52.683392544969465,
      "overlap_obb": 0.03760333191638539,
      "overlap_geometry": 0.00035929545794022777,
      "center_difference": [
        0.5684705985146687,
        -2.8897507302868104,
        -0.04420452314512591
      ],
      "log_obb_volume_ratio": 0.4743308093318761,
      "log_geom_volume_ratio": 1.3257078419639046,
      "source": "curtain:8",
      "target": "wall:2"
    },
    {
      "type": "touching",
      "weight": 0.02560481817690226,
      "weight_inv": 39.05514942894949,
      "overlap_obb": 0.051048155249112284,
      "overlap_geometry": 0.0001614811046922372,
      "center_difference": [
        1.3102466871070864,
        -1.7731583813804677,
        1.195486803115315
      ],
      "log_obb_volume_ratio": 0.46702660520205,
      "log_geom_volume_ratio": 1.1076262405761046,
      "source": "curtain:8",
      "target": "ceiling:9"
    },
    {
      "type": "within",
      "weight": 0.4911403455202207,
      "weight_inv": 2.036077893256336,
      "overlap_obb": 0.9822806910404414,
      "overlap_geometry": 0.0,
      "center_difference": [
        0.7153971986625646,
        -0.13949188292857384,
        -0.15326799887735976
      ],
      "log_obb_volume_ratio": -0.8024281770107964,
      "log_geom_volume_ratio": 1.8886063877156216,
      "source": "blanket:10",
      "target": "bed:18"
    },
    {
      "type": "within",
      "weight": 0.46955235550764757,
      "weight_inv": 2.1296879640160022,
      "overlap_obb": 0.9391047110152951,
      "overlap_geometry": 0.0,
      "center_difference": [
        0.30000020601697036,
        0.5251587730676405,
        -0.15285428772534926
      ],
      "log_obb_volume_ratio": -0.758303427723403,
      "log_geom_volume_ratio": 1.8916812281810442,
      "source": "blanket:11",
      "target": "bed:18"
    },
    {
      "type": "within",
      "weight": 0.4999999903935418,
      "weight_inv": 2.0000000384258336,
      "overlap_obb": 0.9999999807870836,
      "overlap_geometry": 0.0,
      "center_difference": [
        0.04155967162699417,
        -0.612995493217064,
        -0.2481842601491131
      ],
      "log_obb_volume_ratio": -1.4312792447595513,
      "log_geom_volume_ratio": 2.5703887414435007,
      "source": "pillow:12",
      "target": "bed:18"
    },
    {
      "type": "within",
      "weight": 0.5000161392641939,
      "weight_inv": 1.9999354450269642,
      "overlap_obb": 0.9999999823074492,
      "overlap_geometry": 3.229622093844744e-05,
      "center_difference": [
        -0.3435594364982189,
        0.012610368230771662,
        -0.25326888115101176
      ],
      "log_obb_volume_ratio": -1.3913570525907093,
      "log_geom_volume_ratio": 2.5825324905725724,
      "source": "pillow:13",
      "target": "bed:18"
    },
    {
      "type": "within",
      "weight": 0.49999999437128484,
      "weight_inv": 2.000000022514861,
      "overlap_obb": 0.9999999887425697,
      "overlap_geometry": 0.0,
      "center_difference": [
        -0.5575991830919877,
        -0.03129215281409481,
        -0.2827767133127752
      ],
      "log_obb_volume_ratio": -1.172414361571286,
      "log_geom_volume_ratio": 2.5306594393833644,
      "source": "pillow:14",
      "target": "bed:18"
    },
    {
      "type": "within",
      "weight": 0.5000100867610712,
      "weight_inv": 1.999959653769641,
      "overlap_obb": 0.9999999883840559,
      "overlap_geometry": 2.018513808652965e-05,
      "center_difference": [
        -0.11518505376521393,
        -0.7212111019786565,
        -0.28341409530985007
      ],
      "log_obb_volume_ratio": -1.1875961220512077,
      "log_geom_volume_ratio": 2.5938662209384935,
      "source": "pillow:15",
      "target": "bed:18"
    },
    {
      "type": "within",
      "weight": 0.500058532998439,
      "weight_inv": 1.9997658954119308,
      "overlap_obb": 0.9999999921959761,
      "overlap_geometry": 0.00011707380090187197,
      "center_difference": [
        -0.2546240176468871,
        -0.8703484930973087,
        -0.37315353083691005
      ],
      "log_obb_volume_ratio": -0.9949857718023157,
      "log_geom_volume_ratio": 2.47632122751502,
      "source": "pillow:16",
      "target": "bed:18"
    },
    {
      "type": "within",
      "weight": 0.5000141259650341,
      "weight_inv": 1.9999434977361614,
      "overlap_obb": 0.9999999927367472,
      "overlap_geometry": 2.825919332114151e-05,
      "center_difference": [
        -0.7497382670880406,
        -0.14854305256448663,
        -0.3660046645908077
      ],
      "log_obb_volume_ratio": -0.9602100312063957,
      "log_geom_volume_ratio": 2.367353606407278,
      "source": "pillow:17",
      "target": "bed:18"
    },
    {
      "type": "within",
      "weight": 0.499999967901522,
      "weight_inv": 2.0000001283939204,
      "overlap_obb": 0.999999935803044,
      "overlap_geometry": 0.0,
      "center_difference": [
        -1.0688015448740598,
        0.23755795453963569,
        -0.004838039131347394
      ],
      "log_obb_volume_ratio": -2.015481029092479,
      "log_geom_volume_ratio": 3.0672560477916795,
      "source": "table:19",
      "target": "bed:18"
    },
    {
      "type": "within",
      "weight": 0.46370903622685317,
      "weight_inv": 2.156524721055437,
      "overlap_obb": 0.9274180724537063,
      "overlap_geometry": 0.0,
      "center_difference": [
        -0.3619698298058984,
        0.643087820360003,
        0.9603038754981069
      ],
      "log_obb_volume_ratio": -4.357574515366182,
      "log_geom_volume_ratio": 2.3450215970673924,
      "source": "table:20",
      "target": "cabinet:7"
    },
    {
      "type": "within",
      "weight": 0.4997479569531189,
      "weight_inv": 2.001008680649413,
      "overlap_obb": 0.9994959139062378,
      "overlap_geometry": 0.0,
      "center_difference": [
        0.08006567421977656,
        -1.223631930854617,
        0.13230508833893295
      ],
      "log_obb_volume_ratio": -1.3568475934023896,
      "log_geom_volume_ratio": 2.697018182852966,
      "source": "table:20",
      "target": "bed:18"
    },
    {
      "type": "touching",
      "weight": 0.21611880278021686,
      "weight_inv": 4.627084673502265,
      "overlap_obb": 0.4322335685328164,
      "overlap_geometry": 4.03702761730593e-06,
      "center_difference": [
        0.4215636468144779,
        0.6092684765110696,
        0.745250498253387
      ],
      "log_obb_volume_ratio": -3.170068294978352,
      "log_geom_volume_ratio": 3.274583166377355,
      "source": "table:21",
      "target": "curtain:8"
    },
    {
      "type": "weak_touching",
      "weight": 0.01914931058687916,
      "weight_inv": 52.22120114784634,
      "overlap_obb": 0.03829862117375832,
      "overlap_geometry": 0.0,
      "center_difference": [
        0.4508090961180466,
        -2.1368654567144545,
        -0.5101343327156057
      ],
      "log_obb_volume_ratio": -0.4700108885400377,
      "log_geom_volume_ratio": 2.4195463306289016,
      "source": "chair:23",
      "target": "floor:1"
    },
    {
      "type": "touching",
      "weight": 0.03321498543472637,
      "weight_inv": 30.106892624270035,
      "overlap_obb": 0.06639363762089698,
      "overlap_geometry": 3.633324855575337e-05,
      "center_difference": [
        -0.6944420685454756,
        0.16279212772085838,
        0.7383395205528946
      ],
      "log_obb_volume_ratio": -0.9344969310478936,
      "log_geom_volume_ratio": 2.5675338453546757,
      "source": "chair:23",
      "target": "curtain:8"
    },
    {
      "type": "within",
      "weight": 0.47979831528657363,
      "weight_inv": 2.084209068976661,
      "overlap_obb": 0.9593140386399358,
      "overlap_geometry": 0.0002825919332114151,
      "center_difference": [
        0.08514435609705961,
        0.19434360280842933,
        0.03333386798554472
      ],
      "log_obb_volume_ratio": 3.454264754006036,
      "log_geom_volume_ratio": 1.2797677360161983,
      "source": "object:24",
      "target": "chair:23"
    },
    {
      "type": "touching",
      "weight": 0.04520874752608409,
      "weight_inv": 22.11961301124368,
      "overlap_obb": 0.09017527339512982,
      "overlap_geometry": 0.0002422216570383558,
      "center_difference": [
        -2.118175700932798,
        2.0404515433805708,
        0.12073298323527681
      ],
      "log_obb_volume_ratio": 0.12653152354157504,
      "log_geom_volume_ratio": 2.378595680750076,
      "source": "door:26",
      "target": "wall:2"
    },
    {
      "type": "within",
      "weight": 0.4982342036528191,
      "weight_inv": 2.007088218087939,
      "overlap_obb": 0.9964684073056382,
      "overlap_geometry": 0.0,
      "center_difference": [
        1.0729162753792296,
        -1.612039542590432,
        0.19973167794632446
      ],
      "log_obb_volume_ratio": -1.8886799909299337,
      "log_geom_volume_ratio": 4.948885969440899,
      "source": "shelf:33",
      "target": "wall:2"
    },
    {
      "type": "part_within",
      "weight": 0.30402669487742595,
      "weight_inv": 3.289184853991748,
      "overlap_obb": 0.6080493527272346,
      "overlap_geometry": 4.03702761730593e-06,
      "center_difference": [
        0.22369057738812081,
        -0.03957392225126588,
        0.7927224628715553
      ],
      "log_obb_volume_ratio": -4.175883495647086,
      "log_geom_volume_ratio": 4.079893716143634,
      "source": "window:34",
      "target": "curtain:8"
    },
    {
      "type": "within",
      "weight": 0.4822305924612436,
      "weight_inv": 2.0736967244158593,
      "overlap_obb": 0.96435218517682,
      "overlap_geometry": 0.0001089997456672601,
      "center_difference": [
        0.15585915795217595,
        -0.026422455481018403,
        0.7409959820543539
      ],
      "log_obb_volume_ratio": -3.0421080544199506,
      "log_geom_volume_ratio": 1.9016590626524923,
      "source": "-:36",
      "target": "cabinet:7"
    }
  ]
}