{
  "directed": true,
  "multigraph": false,
  "graph": {},
  "nodes": [
    {
      "id": "floor:1",
      "centrality": 0.22210495812955164
    },
    {
      "id": "bathtub:2",
      "centrality": 0.08899759594881677
    },
    {
      "id": "wall:3",
      "centrality": 0.35440850367681515
    },
    {
      "id": "wall:4",
      "centrality": 0.48549819227751334
    },
    {
      "id": "wall:5",
      "centrality": 1.1475923069264191
    },
    {
      "id": "wall:6",
      "centrality": 2.0
    },
    {
      "id": "door:7",
      "centrality": 0.0
    },
    {
      "id": "ceiling:8",
      "centrality": 0.0
    },
    {
      "id": "toilet:9",
      "centrality": 0.0
    },
    {
      "id": "sink:10",
      "centrality": 0.0
    },
    {
      "id": "shelf:11",
      "centrality": 0.17490053723597968
    },
    {
      "id": "clothes:12",
      "centrality": 0.0
    },
    {
      "id": "object:14",
      "centrality": 0.08612363025003052
    },
    {
      "id": "cabinet:16",
      "centrality": 0.18492025848195234
    },
    {
      "id": "sink:17",
      "centrality": 0.16282435610615678
    },
    {
      "id": "window:18",
      "centrality": 0.0
    },
    {
      "id": "counter:19",
      "centrality": 0.0
    },
    {
      "id": "window:20",
      "centrality": 0.15791832874637962
    },
    {
      "id": "object:21",
      "centrality": 0.0
    },
    {
      "id": "-:23",
      "centrality": 0.0
    },
    {
      "id": "shelf:24",
      "centrality": 0.0
    },
    {
      "id": "towel:26",
      "centrality": 0.0
    },
    {
      "id": "towel:27",
      "centrality": 0.1799757981015548
    },
    {
      "id": "-:28",
      "centrality": 0.0
    },
    {
      "id": "shelf:29",
      "centrality": 0.0
    },
    {
      "id": "curtain:30",
      "centrality": 0.0
    },
    {
      "id": "-:31",
      "centrality": 0.0
    }
  ],
  "links": [
    {
      "type": "touching",
      "weight": 0.06950787676991224,
      "weight_inv": 14.38685867661071,
      "overlap_obb": 0.13890952350221905,
      "overlap_geometry": 0.00010623003760543331,
      "center_difference": [
        -0.45820184984489876,
        -1.0468091264195076,
        1.4321995876065905
      ],
      "log_obb_volume_ratio": 0.2625340419127108,
      "log_geom_volume_ratio": 1.1436891674585457,
      "source": "floor:1",
      "target": "wall:5"
    },
    {
      "type": "touching",
      "weight": 0.12138959978781445,
      "weight_inv": 8.237938025563734,
      "overlap_obb": 0.24267296953802348,
      "overlap_geometry": 0.00010623003760543331,
      "center_difference": [
        -0.46736648396243363,
        0.6177632090647934,
        1.4948464559388557
      ],
      "log_obb_volume_ratio": 0.18274607832484038,
      "log_geom_volume_ratio": 1.3901308760416313,
      "source": "floor:1",
      "target": "wall:6"
    },
    {
      "type": "touching",
      "weight": 0.1533597828923776,
      "weight_inv": 6.52061434321255,
      "overlap_obb": 0.3065991717421357,
      "overlap_geometry": 0.00012039404261949109,
      "center_difference": [
        -0.7047639775314116,
        0.11206276693392954,
        -0.27089780341228953
      ],
      "log_obb_volume_ratio": 0.6822014446295254,
      "log_geom_volume_ratio": 0.8521983927146916,
      "source": "bathtub:2",
      "target": "floor:1"
    },
    {
      "type": "touching",
      "weight": 0.1571474957091661,
      "weight_inv": 6.363448526413087,
      "overlap_obb": 0.3139621373005019,
      "overlap_geometry": 0.0003328541178303577,
      "center_difference": [
        0.1803843920782957,
        -0.4520643009557964,
        1.1289605873512027
      ],
      "log_obb_volume_ratio": 0.30021605681759694,
      "log_geom_volume_ratio": 1.1956441897382777,
      "source": "bathtub:2",
      "target": "wall:4"
    },
    {
      "type": "touching",
      "weight": 0.04036844500956862,
      "weight_inv": 24.771823630139032,
      "overlap_obb": 0.0806023319715037,
      "overlap_geometry": 0.00013455804763354886,
      "center_difference": [
        -0.9860743281346315,
        -0.9281472022060323,
        -1.342088730615492
      ],
      "log_obb_volume_ratio": -0.09452366625327119,
      "log_geom_volume_ratio": 0.8272467253762924,
      "source": "wall:3",
      "target": "floor:1"
    },
    {
      "type": "touching",
      "weight": 0.051305367272978485,
      "weight_inv": 19.49113812360681,
      "overlap_obb": 0.10231329044066176,
      "overlap_geometry": 0.00029744410529521326,
      "center_difference": [
        -0.28131035060321985,
        -1.040209969139962,
        -1.0711909272032025
      ],
      "log_obb_volume_ratio": -0.1385568251099248,
      "log_geom_volume_ratio": 0.9707208232828095,
      "source": "wall:3",
      "target": "bathtub:2"
    },
    {
      "type": "touching",
      "weight": 0.06650843506601181,
      "weight_inv": 15.035686811867803,
      "overlap_obb": 0.13300978812951658,
      "overlap_geometry": 7.082002507028887e-06,
      "center_difference": [
        -0.10092595852492414,
        -1.4922742700957583,
        0.05776966014800022
      ],
      "log_obb_volume_ratio": -0.041596983679667035,
      "log_geom_volume_ratio": 1.1606367122160486,
      "source": "wall:3",
      "target": "wall:4"
    },
    {
      "type": "touching",
      "weight": 0.07995262265315288,
      "weight_inv": 12.50740709705244,
      "overlap_obb": 0.15985567128875655,
      "overlap_geometry": 4.9574017549202214e-05,
      "center_difference": [
        -1.4534408120970652,
        -0.3103839931412389,
        0.15275772532336346
      ],
      "log_obb_volume_ratio": -0.01727382931667137,
      "log_geom_volume_ratio": 1.1499812150499162,
      "source": "wall:3",
      "target": "wall:6"
    },
    {
      "type": "weak_touching",
      "weight": 0.011222193656627797,
      "weight_inv": 89.10913771385532,
      "overlap_obb": 0.022444387313255595,
      "overlap_geometry": 0.0,
      "center_difference": [
        -1.343350219454606,
        -0.48268205852978174,
        0.032341196843098226
      ],
      "log_obb_volume_ratio": 0.5965740292368725,
      "log_geom_volume_ratio": 0.8151673203770795,
      "source": "wall:4",
      "target": "wall:5"
    },
    {
      "type": "weak_touching",
      "weight": 0.03858058257214564,
      "weight_inv": 25.919774490963203,
      "overlap_obb": 0.07716116514429128,
      "overlap_geometry": 0.0,
      "center_difference": [
        -0.009164634117534876,
        1.6645723354843012,
        0.06264686833226503
      ],
      "log_obb_volume_ratio": 0.6960852657180402,
      "log_geom_volume_ratio": 1.2154796212074976,
      "source": "wall:5",
      "target": "wall:6"
    },
    {
      "type": "part_within",
      "weight": 0.44461441201674656,
      "weight_inv": 2.249139868102914,
      "overlap_obb": 0.8882373436825091,
      "overlap_geometry": 0.0009914803509840442,
      "center_difference": [
        0.2754583419579021,
        -0.18694342477782988,
        0.06352684401301362
      ],
      "log_obb_volume_ratio": 51.26726062518817,
      "log_geom_volume_ratio": 1.5088323302910254,
      "source": "door:7",
      "target": "wall:3"
    },
    {
      "type": "touching",
      "weight": 0.0375928453088425,
      "weight_inv": 26.600806397721176,
      "overlap_obb": 0.07493782052993898,
      "overlap_geometry": 0.00024787008774601106,
      "center_difference": [
        0.6709309779488901,
        -0.5661207699014813,
        -1.1423327944798096
      ],
      "log_obb_volume_ratio": -0.8910010087708823,
      "log_geom_volume_ratio": 1.1704567701328343,
      "source": "ceiling:8",
      "target": "wall:4"
    },
    {
      "type": "touching",
      "weight": 0.027943821089936313,
      "weight_inv": 35.78608654777496,
      "overlap_obb": 0.05580265814978828,
      "overlap_geometry": 8.498403008434665e-05,
      "center_difference": [
        -0.672419241505716,
        -1.048802828431263,
        -1.1099915976367114
      ],
      "log_obb_volume_ratio": -0.5315480618565632,
      "log_geom_volume_ratio": 0.9541181089263939,
      "source": "ceiling:8",
      "target": "wall:5"
    },
    {
      "type": "touching",
      "weight": 0.046376112904441796,
      "weight_inv": 21.562824854694156,
      "overlap_obb": 0.09253976573367273,
      "overlap_geometry": 0.00021246007521086662,
      "center_difference": [
        -0.6815838756232508,
        0.6157695070530381,
        -1.0473447293044462
      ],
      "log_obb_volume_ratio": -0.37000277387933506,
      "log_geom_volume_ratio": 1.1597111176250672,
      "source": "ceiling:8",
      "target": "wall:6"
    },
    {
      "type": "part_within",
      "weight": 0.2876012469649506,
      "weight_inv": 3.477036384761809,
      "overlap_obb": 0.5751316739048309,
      "overlap_geometry": 7.082002507028888e-05,
      "center_difference": [
        -0.05402101623426025,
        0.9013121319418191,
        -0.29195888977407103
      ],
      "log_obb_volume_ratio": -6.978238531211987,
      "log_geom_volume_ratio": 1.4781946631748146,
      "source": "toilet:9",
      "target": "floor:1"
    },
    {
      "type": "within",
      "weight": 0.47095520835944726,
      "weight_inv": 2.1233441784908975,
      "overlap_obb": 0.9419104167188945,
      "overlap_geometry": 0.0,
      "center_difference": [
        0.3492623738587217,
        1.0669577927278553,
        0.806074803780234
      ],
      "log_obb_volume_ratio": -6.545106458701144,
      "log_geom_volume_ratio": 5.2764543397375725,
      "source": "sink:10",
      "target": "wall:6"
    },
    {
      "type": "within",
      "weight": 0.45233697946253015,
      "weight_inv": 2.2107412071155594,
      "overlap_obb": 0.9046739589250603,
      "overlap_geometry": 0.0,
      "center_difference": [
        -0.00781532603522117,
        0.41448516579406625,
        0.03438045375218157
      ],
      "log_obb_volume_ratio": 8.248349771447623,
      "log_geom_volume_ratio": 2.6034547850862766,
      "source": "sink:10",
      "target": "sink:17"
    },
    {
      "type": "within",
      "weight": 0.4999848354169981,
      "weight_inv": 2.00006066017178,
      "overlap_obb": 0.9999696708339962,
      "overlap_geometry": 0.0,
      "center_difference": [
        -0.1386790697674417,
        0.08989147286821697,
        -0.2380527131782948
      ],
      "log_obb_volume_ratio": 3.5576413800704554,
      "log_geom_volume_ratio": 2.2366426019238816,
      "source": "sink:10",
      "target": "towel:27"
    },
    {
      "type": "part_within",
      "weight": 0.43951848362013585,
      "weight_inv": 2.275217168942259,
      "overlap_obb": 0.878137552921879,
      "overlap_geometry": 0.0008994143183926687,
      "center_difference": [
        -0.11490816877693716,
        0.10884483591722399,
        0.5828677162940766
      ],
      "log_obb_volume_ratio": 0.0872333307315605,
      "log_geom_volume_ratio": 1.3034377707847324,
      "source": "shelf:11",
      "target": "wall:6"
    },
    {
      "type": "within",
      "weight": 0.4995527006987787,
      "weight_inv": 2.001790799251393,
      "overlap_obb": 0.9990629093825153,
      "overlap_geometry": 4.249201504217332e-05,
      "center_difference": [
        -0.5224840319861993,
        -0.4751334948831121,
        0.38498280912236615
      ],
      "log_obb_volume_ratio": -0.8423809887525655,
      "log_geom_volume_ratio": 1.6780771267659722,
      "source": "clothes:12",
      "target": "wall:6"
    },
    {
      "type": "within",
      "weight": 0.49709566509984365,
      "weight_inv": 2.011685215157018,
      "overlap_obb": 0.9939009680968991,
      "overlap_geometry": 0.0002903621027881844,
      "center_difference": [
        0.18966474050884785,
        -0.15467425663760404,
        1.0395863261515477
      ],
      "log_obb_volume_ratio": -1.1783248001293907,
      "log_geom_volume_ratio": 1.1864944858590794,
      "source": "object:14",
      "target": "wall:5"
    },
    {
      "type": "within",
      "weight": 0.4958870804585914,
      "weight_inv": 2.0165881294491683,
      "overlap_obb": 0.9917599969121688,
      "overlap_geometry": 1.4164005014057774e-05,
      "center_difference": [
        0.2346042268938653,
        0.7099758970942025,
        1.1134762947280508
      ],
      "log_obb_volume_ratio": -0.9567496521951097,
      "log_geom_volume_ratio": 1.8289868454779075,
      "source": "cabinet:16",
      "target": "wall:6"
    },
    {
      "type": "part_within",
      "weight": 0.4454116652231854,
      "weight_inv": 2.2451140777799865,
      "overlap_obb": 0.8904479843134984,
      "overlap_geometry": 0.00037534613287253105,
      "center_difference": [
        0.3570776998939429,
        0.6524726269337889,
        0.7716943500280524
      ],
      "log_obb_volume_ratio": -0.7935049603931197,
      "log_geom_volume_ratio": 2.0267124937077465,
      "source": "sink:17",
      "target": "wall:6"
    },
    {
      "type": "within",
      "weight": 0.5000106184542777,
      "weight_inv": 1.9999575270848824,
      "overlap_obb": 0.9999999909010344,
      "overlap_geometry": 2.124600752108666e-05,
      "center_difference": [
        0.22396459123030033,
        -0.07855967437712463,
        0.664404782894845
      ],
      "log_obb_volume_ratio": -2.0119151534691544,
      "log_geom_volume_ratio": 1.9500906401580265,
      "source": "window:18",
      "target": "wall:5"
    },
    {
      "type": "within",
      "weight": 0.4999982352874506,
      "weight_inv": 2.0000070588751115,
      "overlap_obb": 0.9999964705749012,
      "overlap_geometry": 0.0,
      "center_difference": [
        -0.4093507698015212,
        0.4279410127991097,
        1.1234279354479688
      ],
      "log_obb_volume_ratio": -7.442900743841411,
      "log_geom_volume_ratio": 3.609846772064777,
      "source": "counter:19",
      "target": "wall:5"
    },
    {
      "type": "part_within",
      "weight": 0.44002876451751294,
      "weight_inv": 2.2725787053864304,
      "overlap_obb": 0.8800575290350259,
      "overlap_geometry": 0.0,
      "center_difference": [
        0.22861481496845526,
        0.09505327964555721,
        -0.19765749265566201
      ],
      "log_obb_volume_ratio": -0.053852840247326506,
      "log_geom_volume_ratio": 1.1808549144958913,
      "source": "window:20",
      "target": "wall:5"
    },
    {
      "type": "within",
      "weight": 0.5000035162265946,
      "weight_inv": 1.9999859351925318,
      "overlap_obb": 0.9999999504506821,
      "overlap_geometry": 7.082002507028887e-06,
      "center_difference": [
        -0.10593318159720311,
        0.27047392485808786,
        0.5249287253373844
      ],
      "log_obb_volume_ratio": -3.556100516070462,
      "log_geom_volume_ratio": 2.322470160924283,
      "source": "object:21",
      "target": "wall:5"
    },
    {
      "type": "part_within",
      "weight": 0.43870770648303026,
      "weight_inv": 2.2794220051812135,
      "overlap_obb": 0.8774012489610464,
      "overlap_geometry": 1.4164005014057774e-05,
      "center_difference": [
        -0.33454799656565837,
        0.17542064521253065,
        0.7225862179930465
      ],
      "log_obb_volume_ratio": 66.03366692896022,
      "log_geom_volume_ratio": 1.9667701191858518,
      "source": "object:21",
      "target": "window:20"
    },
    {
      "type": "within",
      "weight": 0.4999973958468967,
      "weight_inv": 2.0000104166666666,
      "overlap_obb": 0.9999947916937934,
      "overlap_geometry": 0.0,
      "center_difference": [
        0.49236546272498033,
        0.7305577118517672,
        0.9765769346833018
      ],
      "log_obb_volume_ratio": -13.07036412592366,
      "log_geom_volume_ratio": 4.4569654576043085,
      "source": "-:23",
      "target": "wall:4"
    },
    {
      "type": "part_within",
      "weight": 0.3705417244369764,
      "weight_inv": 2.69875140652368,
      "overlap_obb": 0.7409984648438684,
      "overlap_geometry": 8.498403008434665e-05,
      "center_difference": [
        -0.5908129430764713,
        0.6007826460841479,
        -0.3791452871345274
      ],
      "log_obb_volume_ratio": 118.3147076458258,
      "log_geom_volume_ratio": 2.2888086492118456,
      "source": "shelf:24",
      "target": "wall:3"
    },
    {
      "type": "within",
      "weight": 0.46674836638710704,
      "weight_inv": 2.142482056746247,
      "overlap_obb": 0.9334896507717071,
      "overlap_geometry": 7.082002507028887e-06,
      "center_difference": [
        -0.6917389016013954,
        -0.8914916240116104,
        -0.32137562698652716
      ],
      "log_obb_volume_ratio": -4.921534963007992,
      "log_geom_volume_ratio": 2.656475345512892,
      "source": "shelf:24",
      "target": "wall:4"
    },
    {
      "type": "part_within",
      "weight": 0.42106700489008964,
      "weight_inv": 2.3749189283093513,
      "overlap_obb": 0.8421340097801793,
      "overlap_geometry": 0.0,
      "center_difference": [
        0.584642629538413,
        -0.6114209233945097,
        0.9253091235667807
      ],
      "log_obb_volume_ratio": -2.271729581699846,
      "log_geom_volume_ratio": 1.7264590171186112,
      "source": "towel:26",
      "target": "wall:5"
    },
    {
      "type": "part_within",
      "weight": 0.4306070913947923,
      "weight_inv": 2.322302674488871,
      "overlap_obb": 0.8612141827895846,
      "overlap_geometry": 0.0,
      "center_difference": [
        0.5754779954208781,
        1.0531514120897914,
        0.9879559918990457
      ],
      "log_obb_volume_ratio": -1.5813174895170696,
      "log_geom_volume_ratio": 2.098475752157598,
      "source": "towel:26",
      "target": "wall:6"
    },
    {
      "type": "touching",
      "weight": 0.23925721986118478,
      "weight_inv": 4.179602189560643,
      "overlap_obb": 0.4785073577198625,
      "overlap_geometry": 7.082002507028887e-06,
      "center_difference": [
        0.3949778890295651,
        -0.4567466667569057,
        -0.11427720258476703
      ],
      "log_obb_volume_ratio": 1.927931569844231,
      "log_geom_volume_ratio": 1.4550923225476025,
      "source": "towel:26",
      "target": "object:14"
    },
    {
      "type": "within",
      "weight": 0.45091207445634957,
      "weight_inv": 2.217727261363911,
      "overlap_obb": 0.9018241489126991,
      "overlap_geometry": 0.0,
      "center_difference": [
        0.48794144362616343,
        0.9770663198596382,
        1.044127516958529
      ],
      "log_obb_volume_ratio": -1.8397319345806367,
      "log_geom_volume_ratio": 2.3590958766496493,
      "source": "towel:27",
      "target": "wall:6"
    },
    {
      "type": "part_within",
      "weight": 0.31898068334332613,
      "weight_inv": 3.134986073509904,
      "overlap_obb": 0.6378409726440327,
      "overlap_geometry": 0.00012039404261949109,
      "center_difference": [
        0.25333721673229814,
        0.26709042276543576,
        -0.06934877776952186
      ],
      "log_obb_volume_ratio": 1.922897939246348,
      "log_geom_volume_ratio": 1.2898375308069678,
      "source": "towel:27",
      "target": "cabinet:16"
    },
    {
      "type": "within",
      "weight": 0.4999999252261006,
      "weight_inv": 2.0000002990956425,
      "overlap_obb": 0.9999998504522012,
      "overlap_geometry": 0.0,
      "center_difference": [
        0.7307623738587216,
        0.9275244593945219,
        -0.19105852955309943
      ],
      "log_obb_volume_ratio": -3.1759412141529966,
      "log_geom_volume_ratio": 3.193291733184432,
      "source": "-:28",
      "target": "wall:6"
    },
    {
      "type": "within",
      "weight": 0.5000389415140095,
      "weight_inv": 1.9998442460745494,
      "overlap_obb": 0.9999999810004417,
      "overlap_geometry": 7.790202757731776e-05,
      "center_difference": [
        0.40233069684008815,
        0.558320111568435,
        0.20573525926677638
      ],
      "log_obb_volume_ratio": -1.8674137369713553,
      "log_geom_volume_ratio": 2.502563272679387,
      "source": "shelf:29",
      "target": "wall:6"
    },
    {
      "type": "touching",
      "weight": 0.10487278101306984,
      "weight_inv": 9.535362658833034,
      "overlap_obb": 0.20939854390329526,
      "overlap_geometry": 0.0003470181228444155,
      "center_difference": [
        -0.346815418615687,
        -0.6508224689851536,
        -0.8888554360479195
      ],
      "log_obb_volume_ratio": -4.269702351946226,
      "log_geom_volume_ratio": 1.1575599967054486,
      "source": "curtain:30",
      "target": "bathtub:2"
    },
    {
      "type": "touching",
      "weight": 0.16941445164973473,
      "weight_inv": 5.902684158654335,
      "overlap_obb": 0.3386872632493289,
      "overlap_geometry": 0.00014164005014057776,
      "center_difference": [
        -0.06550506801246714,
        0.38938750015480833,
        0.18233549115528314
      ],
      "log_obb_volume_ratio": 30.815532533737215,
      "log_geom_volume_ratio": 1.192474673398662,
      "source": "curtain:30",
      "target": "wall:3"
    },
    {
      "type": "within",
      "weight": 0.5000247807865478,
      "weight_inv": 1.9999008817662645,
      "overlap_obb": 0.9999999875555464,
      "overlap_geometry": 4.9574017549202214e-05,
      "center_difference": [
        -0.43824103678247883,
        -0.2291722663899256,
        1.1996991784960138
      ],
      "log_obb_volume_ratio": -1.5990485129472738,
      "log_geom_volume_ratio": 2.205220230319745,
      "source": "-:31",
      "target": "wall:6"
    },
    {
      "type": "within",
      "weight": 0.4858854204104256,
      "weight_inv": 2.0580983869721874,
      "overlap_obb": 0.9716716927857528,
      "overlap_geometry": 9.914803509840443e-05,
      "center_difference": [
        -0.3233328680055417,
        -0.3380171023071496,
        0.6168314622019371
      ],
      "log_obb_volume_ratio": -18.33070570087435,
      "log_geom_volume_ratio": 1.6918492618117826,
      "source": "-:31",
      "target": "shelf:11"
    }
  ]
}